{"3059": [{"date": "2023/05/02", "o": 33.4, "h": 33.45, "l": 33.15, "c": 33.25, "v": 784479}, {"date": "2023/05/03", "o": 33.15, "h": 33.15, "l": 32.8, "c": 32.9, "v": 855849}, {"date": "2023/05/04", "o": 33.1, "h": 33.15, "l": 32.8, "c": 32.85, "v": 973588}, {"date": "2023/05/05", "o": 32.85, "h": 33.15, "l": 32.85, "c": 32.9, "v": 480477}, {"date": "2023/05/08", "o": 33.9, "h": 33.9, "l": 33.0, "c": 33.0, "v": 640053}, {"date": "2023/05/09", "o": 33.2, "h": 33.25, "l": 32.55, "c": 33.1, "v": 1111550}, {"date": "2023/05/10", "o": 33.5, "h": 33.55, "l": 32.95, "c": 32.95, "v": 1056807}, {"date": "2023/05/11", "o": 33.2, "h": 33.45, "l": 32.6, "c": 32.8, "v": 910034}, {"date": "2023/05/12", "o": 32.65, "h": 33.25, "l": 32.6, "c": 33.2, "v": 802100}, {"date": "2023/05/15", "o": 33.05, "h": 33.2, "l": 32.8, "c": 32.95, "v": 581245}, {"date": "2023/05/16", "o": 33.15, "h": 33.55, "l": 33.15, "c": 33.3, "v": 927655}, {"date": "2023/05/17", "o": 33.3, "h": 34.85, "l": 33.2, "c": 34.4, "v": 5817486}, {"date": "2023/05/18", "o": 34.4, "h": 34.6, "l": 33.9, "c": 33.9, "v": 1651390}, {"date": "2023/05/19", "o": 34.25, "h": 34.6, "l": 33.85, "c": 34.25, "v": 2113138}, {"date": "2023/05/22", "o": 34.05, "h": 34.4, "l": 34.05, "c": 34.4, "v": 831051}, {"date": "2023/05/23", "o": 34.3, "h": 34.55, "l": 34.2, "c": 34.35, "v": 986725}, {"date": "2023/05/24", "o": 34.4, "h": 34.6, "l": 34.3, "c": 34.45, "v": 818010}, {"date": "2023/05/25", "o": 34.6, "h": 34.75, "l": 34.3, "c": 34.55, "v": 975415}, {"date": "2023/05/26", "o": 35.0, "h": 35.0, "l": 33.85, "c": 33.85, "v": 1246727}, {"date": "2023/05/29", "o": 34.05, "h": 34.8, "l": 34.05, "c": 34.6, "v": 1368833}, {"date": "2023/05/30", "o": 34.8, "h": 34.9, "l": 34.55, "c": 34.65, "v": 1055501}, {"date": "2023/05/31", "o": 34.5, "h": 36.15, "l": 34.5, "c": 35.15, "v": 5537319}, {"date": "2023/06/01", "o": 35.15, "h": 36.9, "l": 35.1, "c": 36.3, "v": 11868475}, {"date": "2023/06/02", "o": 36.4, "h": 36.6, "l": 35.8, "c": 35.95, "v": 3713302}, {"date": "2023/06/05", "o": 36.05, "h": 36.45, "l": 35.9, "c": 36.2, "v": 2308615}, {"date": "2023/06/06", "o": 36.7, "h": 36.7, "l": 35.9, "c": 35.95, "v": 2718334}, {"date": "2023/06/07", "o": 36.2, "h": 36.2, "l": 35.75, "c": 35.85, "v": 1524153}, {"date": "2023/06/08", "o": 35.9, "h": 36.1, "l": 35.35, "c": 35.45, "v": 1478002}, {"date": "2023/06/09", "o": 35.6, "h": 35.95, "l": 35.4, "c": 35.8, "v": 1195552}, {"date": "2023/06/12", "o": 35.6, "h": 35.6, "l": 34.3, "c": 34.3, "v": 3455601}, {"date": "2023/06/13", "o": 34.5, "h": 34.7, "l": 34.45, "c": 34.55, "v": 977559}, {"date": "2023/06/14", "o": 34.55, "h": 35.1, "l": 34.55, "c": 34.85, "v": 1104860}, {"date": "2023/06/15", "o": 34.9, "h": 36.4, "l": 34.7, "c": 36.1, "v": 6776319}, {"date": "2023/06/16", "o": 35.75, "h": 35.95, "l": 35.45, "c": 35.95, "v": 2159500}, {"date": "2023/06/19", "o": 36.0, "h": 36.0, "l": 35.15, "c": 35.15, "v": 1507429}, {"date": "2023/06/20", "o": 35.25, "h": 35.45, "l": 34.9, "c": 35.0, "v": 1189042}, {"date": "2023/06/21", "o": 35.0, "h": 35.65, "l": 35.0, "c": 35.2, "v": 1022541}, {"date": "2023/06/26", "o": 35.2, "h": 35.2, "l": 34.65, "c": 34.65, "v": 968764}, {"date": "2023/06/27", "o": 34.65, "h": 34.7, "l": 34.0, "c": 34.0, "v": 1358908}, {"date": "2023/06/28", "o": 34.25, "h": 34.45, "l": 34.0, "c": 34.0, "v": 782869}, {"date": "2023/06/29", "o": 34.1, "h": 34.6, "l": 34.1, "c": 34.25, "v": 882869}, {"date": "2023/06/30", "o": 34.3, "h": 34.3, "l": 34.05, "c": 34.1, "v": 710607}, {"date": "2023/07/03", "o": 34.3, "h": 34.5, "l": 34.1, "c": 34.15, "v": 1181005}, {"date": "2023/07/04", "o": 34.4, "h": 34.45, "l": 34.0, "c": 34.15, "v": 1131000}, {"date": "2023/07/05", "o": 34.4, "h": 34.75, "l": 34.25, "c": 34.25, "v": 1243035}, {"date": "2023/07/06", "o": 34.2, "h": 34.65, "l": 34.05, "c": 34.5, "v": 1008339}, {"date": "2023/07/07", "o": 34.5, "h": 34.5, "l": 33.5, "c": 33.8, "v": 1571213}, {"date": "2023/07/10", "o": 33.75, "h": 34.3, "l": 33.55, "c": 33.55, "v": 982829}, {"date": "2023/07/11", "o": 33.7, "h": 33.8, "l": 33.5, "c": 33.55, "v": 882120}, {"date": "2023/07/12", "o": 33.65, "h": 33.7, "l": 33.05, "c": 33.15, "v": 1285408}, {"date": "2023/07/13", "o": 33.3, "h": 33.55, "l": 33.1, "c": 33.2, "v": 1417032}, {"date": "2023/07/14", "o": 33.45, "h": 33.45, "l": 33.15, "c": 33.2, "v": 894351}, {"date": "2023/07/17", "o": 33.2, "h": 34.0, "l": 33.1, "c": 33.85, "v": 1335860}, {"date": "2023/07/18", "o": 34.35, "h": 34.35, "l": 33.5, "c": 33.6, "v": 1339282}, {"date": "2023/07/19", "o": 33.7, "h": 33.75, "l": 33.0, "c": 33.05, "v": 1233279}, {"date": "2023/07/20", "o": 33.1, "h": 33.65, "l": 33.1, "c": 33.5, "v": 753738}, {"date": "2023/07/21", "o": 33.35, "h": 33.65, "l": 33.1, "c": 33.5, "v": 715605}, {"date": "2023/07/24", "o": 33.5, "h": 33.5, "l": 32.95, "c": 33.1, "v": 1025999}, {"date": "2023/07/25", "o": 33.1, "h": 34.75, "l": 33.1, "c": 34.4, "v": 4375053}, {"date": "2023/07/26", "o": 34.9, "h": 37.4, "l": 34.7, "c": 36.35, "v": 22475320}, {"date": "2023/07/27", "o": 36.35, "h": 36.6, "l": 35.8, "c": 35.9, "v": 7083922}, {"date": "2023/07/28", "o": 36.2, "h": 36.3, "l": 35.0, "c": 35.25, "v": 3203055}, {"date": "2023/07/31", "o": 36.2, "h": 36.55, "l": 35.5, "c": 35.6, "v": 4549821}, {"date": "2023/08/01", "o": 35.8, "h": 36.2, "l": 35.25, "c": 35.4, "v": 1816995}, {"date": "2023/08/02", "o": 35.25, "h": 35.3, "l": 34.35, "c": 34.5, "v": 2235661}, {"date": "2023/08/04", "o": 34.4, "h": 34.4, "l": 33.95, "c": 34.2, "v": 916691}, {"date": "2023/08/07", "o": 34.2, "h": 34.7, "l": 33.8, "c": 34.5, "v": 862203}, {"date": "2023/08/08", "o": 34.45, "h": 34.45, "l": 33.95, "c": 34.0, "v": 948906}, {"date": "2023/08/09", "o": 33.95, "h": 34.35, "l": 33.8, "c": 34.1, "v": 700106}, {"date": "2023/08/10", "o": 34.2, "h": 34.2, "l": 33.3, "c": 33.4, "v": 1591020}, {"date": "2023/08/11", "o": 33.5, "h": 33.8, "l": 33.1, "c": 33.2, "v": 1047100}, {"date": "2023/08/14", "o": 33.2, "h": 33.45, "l": 32.7, "c": 32.75, "v": 2372244}, {"date": "2023/08/15", "o": 33.0, "h": 33.2, "l": 32.95, "c": 33.05, "v": 911010}, {"date": "2023/08/16", "o": 33.0, "h": 33.7, "l": 32.8, "c": 33.35, "v": 1165030}, {"date": "2023/08/17", "o": 33.3, "h": 33.95, "l": 33.05, "c": 33.85, "v": 1079004}, {"date": "2023/08/18", "o": 33.85, "h": 34.3, "l": 33.35, "c": 33.4, "v": 1315433}, {"date": "2023/08/21", "o": 33.8, "h": 34.0, "l": 33.6, "c": 33.75, "v": 608503}, {"date": "2023/08/22", "o": 34.0, "h": 34.2, "l": 33.75, "c": 33.85, "v": 920368}, {"date": "2023/08/23", "o": 33.85, "h": 34.6, "l": 33.85, "c": 34.5, "v": 1533873}, {"date": "2023/08/24", "o": 34.9, "h": 34.9, "l": 34.05, "c": 34.1, "v": 1353100}, {"date": "2023/08/25", "o": 33.8, "h": 34.2, "l": 33.65, "c": 33.8, "v": 954626}, {"date": "2023/08/28", "o": 34.0, "h": 34.0, "l": 33.3, "c": 33.35, "v": 908469}, {"date": "2023/08/29", "o": 33.55, "h": 34.2, "l": 33.55, "c": 34.05, "v": 1023050}, {"date": "2023/08/30", "o": 34.4, "h": 34.6, "l": 34.1, "c": 34.35, "v": 1137100}, {"date": "2023/08/31", "o": 34.45, "h": 35.8, "l": 34.35, "c": 35.65, "v": 4554993}, {"date": "2023/09/01", "o": 36.0, "h": 36.65, "l": 35.75, "c": 36.1, "v": 9370621}, {"date": "2023/09/04", "o": 36.4, "h": 36.4, "l": 35.85, "c": 35.9, "v": 2959940}, {"date": "2023/09/05", "o": 36.05, "h": 36.65, "l": 35.95, "c": 36.3, "v": 4868320}, {"date": "2023/09/06", "o": 36.5, "h": 36.8, "l": 36.25, "c": 36.4, "v": 3148589}, {"date": "2023/09/07", "o": 36.25, "h": 36.45, "l": 35.85, "c": 35.95, "v": 2126629}, {"date": "2023/09/08", "o": 35.95, "h": 36.05, "l": 35.65, "c": 35.75, "v": 1048601}, {"date": "2023/09/11", "o": 35.6, "h": 35.65, "l": 34.55, "c": 34.65, "v": 1769455}, {"date": "2023/09/12", "o": 34.7, "h": 35.1, "l": 34.7, "c": 34.95, "v": 848128}, {"date": "2023/09/13", "o": 35.05, "h": 35.1, "l": 34.4, "c": 34.45, "v": 1341169}, {"date": "2023/09/14", "o": 34.5, "h": 34.8, "l": 34.5, "c": 34.65, "v": 1048349}, {"date": "2023/09/15", "o": 34.95, "h": 34.95, "l": 34.45, "c": 34.6, "v": 1301103}, {"date": "2023/09/18", "o": 34.6, "h": 35.25, "l": 34.45, "c": 34.85, "v": 2317606}, {"date": "2023/09/19", "o": 34.0, "h": 34.0, "l": 33.35, "c": 33.4, "v": 2820692}, {"date": "2023/09/20", "o": 33.45, "h": 33.75, "l": 33.25, "c": 33.7, "v": 966723}, {"date": "2023/09/21", "o": 33.6, "h": 33.6, "l": 33.2, "c": 33.3, "v": 1078664}, {"date": "2023/09/22", "o": 33.2, "h": 33.45, "l": 33.0, "c": 33.4, "v": 942460}, {"date": "2023/09/25", "o": 33.5, "h": 34.0, "l": 33.4, "c": 33.95, "v": 652165}, {"date": "2023/09/26", "o": 33.95, "h": 34.35, "l": 33.7, "c": 33.7, "v": 906136}, {"date": "2023/09/27", "o": 33.6, "h": 33.8, "l": 33.35, "c": 33.45, "v": 675191}, {"date": "2023/09/28", "o": 33.6, "h": 33.6, "l": 33.35, "c": 33.4, "v": 701003}, {"date": "2023/10/02", "o": 33.4, "h": 33.9, "l": 33.4, "c": 33.85, "v": 646593}, {"date": "2023/10/03", "o": 33.75, "h": 34.2, "l": 33.75, "c": 33.85, "v": 887750}, {"date": "2023/10/04", "o": 33.7, "h": 34.0, "l": 33.5, "c": 34.0, "v": 632485}, {"date": "2023/10/05", "o": 34.15, "h": 35.0, "l": 33.85, "c": 34.65, "v": 4330407}, {"date": "2023/10/06", "o": 34.85, "h": 34.9, "l": 34.1, "c": 34.15, "v": 1415802}, {"date": "2023/10/11", "o": 34.15, "h": 34.5, "l": 33.5, "c": 34.1, "v": 1574041}, {"date": "2023/10/12", "o": 34.3, "h": 34.3, "l": 34.0, "c": 34.3, "v": 560477}, {"date": "2023/10/13", "o": 34.25, "h": 35.4, "l": 34.2, "c": 34.85, "v": 6186540}, {"date": "2023/10/16", "o": 34.6, "h": 34.7, "l": 33.75, "c": 33.75, "v": 1516028}, {"date": "2023/10/17", "o": 34.0, "h": 34.0, "l": 33.55, "c": 33.6, "v": 965040}, {"date": "2023/10/18", "o": 33.85, "h": 34.05, "l": 33.6, "c": 33.65, "v": 1071105}, {"date": "2023/10/19", "o": 33.65, "h": 35.15, "l": 33.2, "c": 34.3, "v": 6561917}, {"date": "2023/10/20", "o": 34.3, "h": 34.3, "l": 33.65, "c": 33.75, "v": 1312140}, {"date": "2023/10/23", "o": 33.75, "h": 34.05, "l": 33.6, "c": 33.6, "v": 825875}, {"date": "2023/10/24", "o": 33.7, "h": 33.8, "l": 33.4, "c": 33.75, "v": 798401}, {"date": "2023/10/25", "o": 33.95, "h": 34.7, "l": 33.95, "c": 34.55, "v": 1731120}, {"date": "2023/10/26", "o": 34.0, "h": 34.3, "l": 33.55, "c": 33.6, "v": 1345349}, {"date": "2023/10/27", "o": 33.8, "h": 35.1, "l": 33.6, "c": 33.95, "v": 9248912}, {"date": "2023/10/30", "o": 33.95, "h": 34.25, "l": 33.75, "c": 34.1, "v": 1411100}, {"date": "2023/10/31", "o": 34.25, "h": 34.5, "l": 33.6, "c": 33.65, "v": 1466624}, {"date": "2023/11/01", "o": 33.95, "h": 34.0, "l": 33.3, "c": 33.5, "v": 1529655}, {"date": "2023/11/02", "o": 33.65, "h": 34.0, "l": 33.65, "c": 33.8, "v": 842477}, {"date": "2023/11/03", "o": 34.0, "h": 34.25, "l": 33.65, "c": 33.75, "v": 827197}, {"date": "2023/11/06", "o": 33.85, "h": 34.3, "l": 33.85, "c": 34.1, "v": 1237760}, {"date": "2023/11/07", "o": 34.05, "h": 34.15, "l": 33.85, "c": 33.9, "v": 588869}, {"date": "2023/11/08", "o": 33.95, "h": 34.05, "l": 33.7, "c": 33.7, "v": 704560}, {"date": "2023/11/09", "o": 33.75, "h": 33.75, "l": 33.4, "c": 33.45, "v": 979663}, {"date": "2023/11/10", "o": 33.45, "h": 33.55, "l": 33.05, "c": 33.1, "v": 1228308}, {"date": "2023/11/13", "o": 33.6, "h": 33.7, "l": 33.1, "c": 33.65, "v": 1278200}, {"date": "2023/11/14", "o": 34.0, "h": 34.55, "l": 33.9, "c": 33.9, "v": 2758014}, {"date": "2023/11/15", "o": 34.2, "h": 34.85, "l": 34.05, "c": 34.65, "v": 3475660}, {"date": "2023/11/16", "o": 34.65, "h": 35.8, "l": 34.65, "c": 35.35, "v": 6348417}, {"date": "2023/11/17", "o": 35.35, "h": 36.0, "l": 35.35, "c": 35.7, "v": 3706548}, {"date": "2023/11/20", "o": 36.5, "h": 39.25, "l": 36.4, "c": 39.25, "v": 25645413}, {"date": "2023/11/21", "o": 40.45, "h": 41.05, "l": 37.65, "c": 38.3, "v": 39390395}, {"date": "2023/11/22", "o": 37.85, "h": 41.3, "l": 37.4, "c": 40.8, "v": 32709045}, {"date": "2023/11/23", "o": 40.5, "h": 42.0, "l": 39.5, "c": 40.3, "v": 25341029}, {"date": "2023/11/24", "o": 40.0, "h": 40.4, "l": 38.95, "c": 39.75, "v": 8258098}, {"date": "2023/11/27", "o": 40.25, "h": 40.65, "l": 38.65, "c": 39.0, "v": 8822861}, {"date": "2023/11/28", "o": 39.45, "h": 39.7, "l": 39.0, "c": 39.6, "v": 4188134}, {"date": "2023/11/29", "o": 39.8, "h": 40.1, "l": 39.35, "c": 39.4, "v": 4314414}, {"date": "2023/11/30", "o": 39.8, "h": 40.2, "l": 38.95, "c": 39.35, "v": 10945929}, {"date": "2023/12/01", "o": 39.4, "h": 39.4, "l": 38.4, "c": 38.55, "v": 6148658}, {"date": "2023/12/04", "o": 39.3, "h": 39.6, "l": 38.25, "c": 38.3, "v": 5754174}, {"date": "2023/12/05", "o": 38.3, "h": 38.35, "l": 37.55, "c": 38.1, "v": 3272792}, {"date": "2023/12/06", "o": 38.45, "h": 38.5, "l": 37.65, "c": 38.15, "v": 3422902}, {"date": "2023/12/07", "o": 38.3, "h": 39.6, "l": 38.15, "c": 38.2, "v": 12690461}, {"date": "2023/12/08", "o": 38.3, "h": 38.5, "l": 37.95, "c": 38.35, "v": 3838945}, {"date": "2023/12/11", "o": 38.35, "h": 38.35, "l": 36.85, "c": 37.0, "v": 7070631}, {"date": "2023/12/12", "o": 37.35, "h": 37.65, "l": 37.0, "c": 37.1, "v": 2509758}, {"date": "2023/12/13", "o": 37.1, "h": 37.8, "l": 37.0, "c": 37.0, "v": 2239560}, {"date": "2023/12/14", "o": 37.45, "h": 37.8, "l": 37.2, "c": 37.6, "v": 2391861}, {"date": "2023/12/15", "o": 37.8, "h": 37.8, "l": 36.85, "c": 36.95, "v": 3201352}, {"date": "2023/12/18", "o": 36.9, "h": 39.3, "l": 36.9, "c": 37.2, "v": 4547480}, {"date": "2023/12/19", "o": 37.2, "h": 37.2, "l": 36.1, "c": 36.9, "v": 2658126}, {"date": "2023/12/20", "o": 37.3, "h": 37.7, "l": 37.2, "c": 37.6, "v": 1627376}, {"date": "2023/12/21", "o": 37.3, "h": 37.8, "l": 37.15, "c": 37.75, "v": 1544856}, {"date": "2023/12/22", "o": 37.7, "h": 37.9, "l": 37.15, "c": 37.15, "v": 1511398}, {"date": "2023/12/25", "o": 37.35, "h": 37.35, "l": 36.6, "c": 36.65, "v": 1312860}, {"date": "2023/12/26", "o": 36.9, "h": 37.45, "l": 36.9, "c": 37.3, "v": 1117494}, {"date": "2023/12/27", "o": 37.4, "h": 37.9, "l": 37.2, "c": 37.75, "v": 1743050}, {"date": "2023/12/28", "o": 37.9, "h": 37.9, "l": 37.4, "c": 37.4, "v": 1203272}, {"date": "2023/12/29", "o": 37.5, "h": 37.5, "l": 37.2, "c": 37.35, "v": 973786}, {"date": "2024/01/02", "o": 37.4, "h": 38.5, "l": 37.4, "c": 38.0, "v": 3701799}, {"date": "2024/01/03", "o": 37.75, "h": 38.05, "l": 37.55, "c": 37.6, "v": 1335357}, {"date": "2024/01/04", "o": 37.8, "h": 38.25, "l": 37.15, "c": 37.15, "v": 2049165}, {"date": "2024/01/05", "o": 37.3, "h": 37.4, "l": 36.7, "c": 36.75, "v": 1293500}, {"date": "2024/01/08", "o": 36.75, "h": 37.1, "l": 36.0, "c": 36.05, "v": 2143221}, {"date": "2024/01/09", "o": 36.35, "h": 36.4, "l": 35.0, "c": 35.15, "v": 2362556}, {"date": "2024/01/10", "o": 35.2, "h": 35.3, "l": 34.5, "c": 34.5, "v": 1637808}, {"date": "2024/01/11", "o": 34.95, "h": 35.0, "l": 34.5, "c": 34.85, "v": 1089709}, {"date": "2024/01/12", "o": 34.7, "h": 34.75, "l": 34.2, "c": 34.3, "v": 1705151}, {"date": "2024/01/15", "o": 34.45, "h": 35.05, "l": 34.45, "c": 35.05, "v": 923738}, {"date": "2024/01/16", "o": 35.25, "h": 35.55, "l": 34.75, "c": 34.75, "v": 1825161}, {"date": "2024/01/17", "o": 34.7, "h": 35.85, "l": 34.7, "c": 35.2, "v": 3954481}, {"date": "2024/01/18", "o": 35.15, "h": 35.35, "l": 34.55, "c": 35.0, "v": 1481186}, {"date": "2024/01/19", "o": 35.1, "h": 35.55, "l": 34.5, "c": 35.3, "v": 2400410}, {"date": "2024/01/22", "o": 35.95, "h": 36.4, "l": 35.0, "c": 36.3, "v": 6730049}, {"date": "2024/01/23", "o": 37.1, "h": 38.45, "l": 37.0, "c": 37.65, "v": 19401625}, {"date": "2024/01/24", "o": 37.7, "h": 38.2, "l": 37.1, "c": 37.25, "v": 6513103}, {"date": "2024/01/25", "o": 37.5, "h": 37.65, "l": 36.8, "c": 37.1, "v": 3172981}, {"date": "2024/01/26", "o": 37.3, "h": 37.3, "l": 36.4, "c": 36.45, "v": 2492271}, {"date": "2024/01/29", "o": 36.6, "h": 38.1, "l": 36.55, "c": 37.4, "v": 5948526}, {"date": "2024/01/30", "o": 37.4, "h": 37.55, "l": 37.0, "c": 37.0, "v": 1462014}, {"date": "2024/01/31", "o": 37.0, "h": 37.0, "l": 36.6, "c": 36.65, "v": 1341414}, {"date": "2024/02/01", "o": 36.7, "h": 36.7, "l": 36.35, "c": 36.45, "v": 1213590}, {"date": "2024/02/02", "o": 36.65, "h": 37.3, "l": 36.15, "c": 36.15, "v": 1949564}, {"date": "2024/02/05", "o": 36.1, "h": 36.55, "l": 35.6, "c": 36.4, "v": 2015861}, {"date": "2024/02/15", "o": 36.3, "h": 36.3, "l": 35.1, "c": 35.25, "v": 2640889}, {"date": "2024/02/16", "o": 35.35, "h": 36.45, "l": 35.35, "c": 36.45, "v": 1789992}, {"date": "2024/02/19", "o": 36.6, "h": 36.7, "l": 36.1, "c": 36.45, "v": 1467172}, {"date": "2024/02/20", "o": 36.45, "h": 36.45, "l": 35.55, "c": 35.65, "v": 1917143}, {"date": "2024/02/21", "o": 35.65, "h": 36.0, "l": 35.45, "c": 35.6, "v": 1478397}, {"date": "2024/02/22", "o": 35.9, "h": 36.1, "l": 35.5, "c": 35.6, "v": 1206746}, {"date": "2024/02/23", "o": 35.75, "h": 35.8, "l": 34.85, "c": 34.9, "v": 2651215}, {"date": "2024/02/26", "o": 34.95, "h": 35.35, "l": 34.95, "c": 35.15, "v": 1244389}, {"date": "2024/02/27", "o": 35.5, "h": 35.75, "l": 34.75, "c": 34.95, "v": 1846720}, {"date": "2024/02/29", "o": 35.1, "h": 35.15, "l": 34.75, "c": 34.8, "v": 1580492}, {"date": "2024/03/01", "o": 34.9, "h": 35.1, "l": 34.8, "c": 34.85, "v": 977106}, {"date": "2024/03/04", "o": 35.05, "h": 35.5, "l": 34.9, "c": 35.2, "v": 1846432}, {"date": "2024/03/05", "o": 35.4, "h": 35.7, "l": 34.8, "c": 35.0, "v": 1584420}, {"date": "2024/03/06", "o": 35.05, "h": 35.05, "l": 34.5, "c": 34.55, "v": 2145491}, {"date": "2024/03/07", "o": 34.6, "h": 34.85, "l": 34.0, "c": 34.0, "v": 2561659}, {"date": "2024/03/08", "o": 34.0, "h": 34.25, "l": 33.5, "c": 33.6, "v": 2088605}, {"date": "2024/03/11", "o": 33.15, "h": 33.9, "l": 33.15, "c": 33.7, "v": 1703508}, {"date": "2024/03/12", "o": 33.95, "h": 34.3, "l": 33.85, "c": 34.1, "v": 1145718}, {"date": "2024/03/13", "o": 34.3, "h": 34.3, "l": 33.25, "c": 33.25, "v": 1939532}, {"date": "2024/03/14", "o": 33.3, "h": 33.7, "l": 33.2, "c": 33.25, "v": 1254425}, {"date": "2024/03/15", "o": 33.25, "h": 33.45, "l": 33.15, "c": 33.15, "v": 677538}, {"date": "2024/03/18", "o": 33.15, "h": 33.4, "l": 32.95, "c": 33.4, "v": 830107}, {"date": "2024/03/19", "o": 33.5, "h": 35.1, "l": 33.2, "c": 34.75, "v": 6719326}, {"date": "2024/03/20", "o": 34.85, "h": 35.6, "l": 34.1, "c": 35.55, "v": 9027903}, {"date": "2024/03/21", "o": 35.65, "h": 35.8, "l": 34.75, "c": 35.15, "v": 4763665}, {"date": "2024/03/22", "o": 35.0, "h": 36.65, "l": 34.5, "c": 36.15, "v": 10782221}, {"date": "2024/03/25", "o": 39.7, "h": 39.75, "l": 37.8, "c": 38.7, "v": 45127861}, {"date": "2024/03/26", "o": 38.75, "h": 38.9, "l": 36.15, "c": 36.25, "v": 18705575}, {"date": "2024/03/27", "o": 36.4, "h": 36.9, "l": 36.35, "c": 36.85, "v": 4918380}, {"date": "2024/03/28", "o": 36.65, "h": 37.15, "l": 36.2, "c": 36.3, "v": 3907480}, {"date": "2024/03/29", "o": 36.45, "h": 36.65, "l": 35.9, "c": 35.95, "v": 1970000}, {"date": "2024/04/01", "o": 36.3, "h": 39.1, "l": 36.05, "c": 38.8, "v": 16428373}, {"date": "2024/04/02", "o": 39.35, "h": 39.4, "l": 38.1, "c": 38.55, "v": 11160258}, {"date": "2024/04/03", "o": 38.0, "h": 38.55, "l": 37.5, "c": 37.75, "v": 4869813}, {"date": "2024/04/08", "o": 38.8, "h": 40.8, "l": 38.3, "c": 40.05, "v": 25262404}, {"date": "2024/04/09", "o": 40.05, "h": 40.1, "l": 38.85, "c": 38.85, "v": 8461333}, {"date": "2024/04/10", "o": 39.1, "h": 41.75, "l": 38.85, "c": 41.2, "v": 26540090}, {"date": "2024/04/11", "o": 40.4, "h": 40.6, "l": 39.5, "c": 39.9, "v": 9660813}, {"date": "2024/04/12", "o": 40.45, "h": 41.2, "l": 40.1, "c": 41.0, "v": 12663763}, {"date": "2024/04/15", "o": 40.65, "h": 42.65, "l": 39.8, "c": 40.8, "v": 23975473}, {"date": "2024/04/16", "o": 40.55, "h": 40.55, "l": 37.6, "c": 38.2, "v": 13812650}, {"date": "2024/04/17", "o": 38.7, "h": 39.6, "l": 38.5, "c": 38.85, "v": 5471321}, {"date": "2024/04/18", "o": 38.85, "h": 39.1, "l": 38.05, "c": 38.35, "v": 4298543}, {"date": "2024/04/19", "o": 37.9, "h": 38.05, "l": 36.25, "c": 37.35, "v": 5598904}, {"date": "2024/04/22", "o": 37.5, "h": 38.15, "l": 36.3, "c": 36.4, "v": 2703041}, {"date": "2024/04/23", "o": 36.9, "h": 39.4, "l": 36.55, "c": 38.55, "v": 9831359}, {"date": "2024/04/24", "o": 38.85, "h": 39.55, "l": 38.7, "c": 38.95, "v": 7101718}, {"date": "2024/04/25", "o": 38.65, "h": 40.8, "l": 38.6, "c": 39.85, "v": 11549927}, {"date": "2024/04/26", "o": 39.95, "h": 40.3, "l": 39.05, "c": 39.05, "v": 6189371}, {"date": "2024/04/29", "o": 39.5, "h": 40.2, "l": 39.2, "c": 39.2, "v": 3269502}, {"date": "2024/04/30", "o": 38.95, "h": 39.7, "l": 38.95, "c": 39.0, "v": 2919300}, {"date": "2024/05/02", "o": 39.0, "h": 39.3, "l": 38.3, "c": 38.55, "v": 2502139}, {"date": "2024/05/03", "o": 38.95, "h": 39.05, "l": 37.8, "c": 37.85, "v": 2807875}, {"date": "2024/05/06", "o": 38.4, "h": 38.75, "l": 37.7, "c": 37.8, "v": 2661168}, {"date": "2024/05/07", "o": 38.05, "h": 40.5, "l": 37.7, "c": 39.25, "v": 10626534}, {"date": "2024/05/08", "o": 39.45, "h": 40.15, "l": 38.9, "c": 39.0, "v": 5352985}, {"date": "2024/05/09", "o": 39.05, "h": 40.3, "l": 38.6, "c": 38.6, "v": 3611166}, {"date": "2024/05/10", "o": 38.95, "h": 39.2, "l": 38.0, "c": 38.6, "v": 2409134}, {"date": "2024/05/13", "o": 39.05, "h": 39.8, "l": 37.9, "c": 39.1, "v": 5621743}, {"date": "2024/05/14", "o": 39.1, "h": 39.85, "l": 38.7, "c": 39.45, "v": 4291404}, {"date": "2024/05/15", "o": 39.85, "h": 40.6, "l": 39.65, "c": 39.95, "v": 10043473}, {"date": "2024/05/16", "o": 41.0, "h": 43.9, "l": 40.85, "c": 43.9, "v": 27068512}, {"date": "2024/05/17", "o": 45.8, "h": 45.8, "l": 41.2, "c": 41.85, "v": 50437200}, {"date": "2024/05/20", "o": 42.25, "h": 42.7, "l": 41.15, "c": 41.3, "v": 13006973}, {"date": "2024/05/21", "o": 41.3, "h": 43.0, "l": 40.85, "c": 42.0, "v": 13452798}, {"date": "2024/05/22", "o": 42.0, "h": 44.15, "l": 41.7, "c": 43.35, "v": 25229426}, {"date": "2024/05/23", "o": 44.0, "h": 44.3, "l": 42.1, "c": 42.55, "v": 19903378}, {"date": "2024/05/24", "o": 42.1, "h": 42.75, "l": 41.3, "c": 42.35, "v": 7687881}, {"date": "2024/05/27", "o": 42.55, "h": 45.1, "l": 42.3, "c": 44.0, "v": 19396937}, {"date": "2024/05/28", "o": 44.25, "h": 44.3, "l": 43.0, "c": 43.15, "v": 9266860}, {"date": "2024/05/29", "o": 43.25, "h": 44.4, "l": 43.0, "c": 43.7, "v": 9182861}, {"date": "2024/05/30", "o": 43.25, "h": 43.3, "l": 41.6, "c": 41.6, "v": 10024393}, {"date": "2024/05/31", "o": 42.0, "h": 44.4, "l": 41.75, "c": 43.3, "v": 20705940}, {"date": "2024/06/03", "o": 44.55, "h": 46.1, "l": 43.8, "c": 44.0, "v": 35253124}, {"date": "2024/06/04", "o": 44.0, "h": 44.7, "l": 42.4, "c": 42.8, "v": 10705410}, {"date": "2024/06/05", "o": 43.45, "h": 43.45, "l": 41.95, "c": 42.25, "v": 5832059}, {"date": "2024/06/06", "o": 42.8, "h": 43.05, "l": 41.5, "c": 41.6, "v": 5151016}, {"date": "2024/06/07", "o": 42.0, "h": 44.3, "l": 41.8, "c": 43.0, "v": 10964623}, {"date": "2024/06/11", "o": 43.05, "h": 43.05, "l": 41.1, "c": 41.35, "v": 6140554}, {"date": "2024/06/12", "o": 41.5, "h": 41.9, "l": 40.7, "c": 41.75, "v": 4402013}, {"date": "2024/06/13", "o": 42.1, "h": 42.8, "l": 40.8, "c": 40.8, "v": 5889865}, {"date": "2024/06/14", "o": 41.15, "h": 41.15, "l": 40.35, "c": 40.4, "v": 4465844}, {"date": "2024/06/17", "o": 40.65, "h": 40.8, "l": 39.85, "c": 40.2, "v": 4225588}, {"date": "2024/06/18", "o": 40.35, "h": 40.7, "l": 39.75, "c": 39.9, "v": 3052605}, {"date": "2024/06/19", "o": 40.15, "h": 40.3, "l": 39.05, "c": 39.1, "v": 4382910}, {"date": "2024/06/20", "o": 39.0, "h": 39.45, "l": 38.95, "c": 39.2, "v": 3478336}, {"date": "2024/06/21", "o": 39.2, "h": 39.9, "l": 39.05, "c": 39.45, "v": 2937007}, {"date": "2024/06/24", "o": 39.45, "h": 39.8, "l": 39.1, "c": 39.3, "v": 2298250}, {"date": "2024/06/25", "o": 39.3, "h": 39.95, "l": 38.45, "c": 39.85, "v": 2842251}, {"date": "2024/06/26", "o": 39.85, "h": 40.15, "l": 39.15, "c": 39.15, "v": 2928257}, {"date": "2024/06/27", "o": 39.15, "h": 39.2, "l": 38.5, "c": 38.55, "v": 2751251}, {"date": "2024/06/28", "o": 38.7, "h": 40.2, "l": 38.6, "c": 39.9, "v": 5262255}, {"date": "2024/07/01", "o": 40.0, "h": 40.25, "l": 39.35, "c": 39.35, "v": 3143807}, {"date": "2024/07/02", "o": 39.5, "h": 41.9, "l": 39.0, "c": 41.7, "v": 16402855}, {"date": "2024/07/03", "o": 41.25, "h": 41.45, "l": 40.9, "c": 41.05, "v": 5540440}, {"date": "2024/07/04", "o": 41.4, "h": 42.2, "l": 41.15, "c": 41.25, "v": 5767922}, {"date": "2024/07/05", "o": 41.3, "h": 42.5, "l": 41.3, "c": 41.9, "v": 8031390}, {"date": "2024/07/08", "o": 42.95, "h": 45.5, "l": 42.65, "c": 43.05, "v": 20524063}, {"date": "2024/07/09", "o": 44.0, "h": 44.0, "l": 41.6, "c": 42.15, "v": 7271371}, {"date": "2024/07/10", "o": 42.6, "h": 43.45, "l": 42.05, "c": 42.1, "v": 4609464}, {"date": "2024/07/11", "o": 42.7, "h": 43.45, "l": 42.35, "c": 42.55, "v": 5346557}, {"date": "2024/07/12", "o": 42.15, "h": 43.0, "l": 41.75, "c": 42.2, "v": 2885954}, {"date": "2024/07/15", "o": 42.7, "h": 43.25, "l": 41.85, "c": 41.9, "v": 3701195}, {"date": "2024/07/16", "o": 42.2, "h": 42.75, "l": 41.45, "c": 41.85, "v": 3295295}, {"date": "2024/07/17", "o": 42.0, "h": 42.4, "l": 41.3, "c": 41.3, "v": 2991231}, {"date": "2024/07/18", "o": 40.8, "h": 40.85, "l": 40.0, "c": 40.5, "v": 3097409}, {"date": "2024/07/19", "o": 40.5, "h": 40.6, "l": 39.2, "c": 39.25, "v": 2981154}, {"date": "2024/07/22", "o": 39.05, "h": 39.4, "l": 38.1, "c": 38.25, "v": 3325519}, {"date": "2024/07/23", "o": 38.9, "h": 39.15, "l": 38.1, "c": 38.25, "v": 1776523}, {"date": "2024/07/26", "o": 37.5, "h": 37.6, "l": 36.85, "c": 37.5, "v": 2092118}, {"date": "2024/07/29", "o": 38.0, "h": 38.15, "l": 36.75, "c": 36.75, "v": 2033111}, {"date": "2024/07/30", "o": 36.95, "h": 37.35, "l": 36.05, "c": 37.3, "v": 1719050}, {"date": "2024/07/31", "o": 36.85, "h": 37.6, "l": 36.85, "c": 37.35, "v": 988877}, {"date": "2024/08/01", "o": 37.7, "h": 38.75, "l": 37.7, "c": 38.45, "v": 2086944}, {"date": "2024/08/02", "o": 37.55, "h": 38.1, "l": 37.2, "c": 37.25, "v": 1607036}, {"date": "2024/08/05", "o": 35.75, "h": 36.0, "l": 33.55, "c": 33.55, "v": 3694596}, {"date": "2024/08/06", "o": 32.65, "h": 34.05, "l": 30.85, "c": 33.0, "v": 3625940}, {"date": "2024/08/07", "o": 33.0, "h": 35.3, "l": 33.0, "c": 35.1, "v": 1965162}, {"date": "2024/08/08", "o": 34.4, "h": 34.95, "l": 33.8, "c": 34.35, "v": 1392002}, {"date": "2024/08/09", "o": 35.6, "h": 35.9, "l": 34.55, "c": 34.55, "v": 1568552}, {"date": "2024/08/12", "o": 34.8, "h": 35.25, "l": 34.55, "c": 34.75, "v": 1630907}, {"date": "2024/08/13", "o": 35.0, "h": 35.3, "l": 34.3, "c": 35.1, "v": 1917139}, {"date": "2024/08/14", "o": 35.6, "h": 35.8, "l": 34.7, "c": 34.85, "v": 1360001}, {"date": "2024/08/15", "o": 34.9, "h": 35.15, "l": 34.55, "c": 34.8, "v": 949001}, {"date": "2024/08/16", "o": 35.2, "h": 35.8, "l": 35.2, "c": 35.35, "v": 1458499}, {"date": "2024/08/19", "o": 35.65, "h": 36.4, "l": 35.3, "c": 36.2, "v": 1994875}, {"date": "2024/08/20", "o": 36.5, "h": 38.45, "l": 36.1, "c": 37.45, "v": 8604501}, {"date": "2024/08/21", "o": 37.4, "h": 37.85, "l": 37.0, "c": 37.7, "v": 3554031}, {"date": "2024/08/22", "o": 37.95, "h": 38.4, "l": 37.45, "c": 38.05, "v": 4709602}, {"date": "2024/08/23", "o": 37.7, "h": 37.75, "l": 37.0, "c": 37.45, "v": 1964053}, {"date": "2024/08/26", "o": 37.6, "h": 37.85, "l": 37.0, "c": 37.05, "v": 1449951}, {"date": "2024/08/27", "o": 37.1, "h": 37.2, "l": 36.65, "c": 37.2, "v": 1177511}, {"date": "2024/08/28", "o": 37.25, "h": 38.65, "l": 36.8, "c": 38.65, "v": 7654290}, {"date": "2024/08/29", "o": 37.85, "h": 38.55, "l": 37.5, "c": 38.1, "v": 3986337}, {"date": "2024/08/30", "o": 38.2, "h": 39.0, "l": 38.15, "c": 38.15, "v": 3127052}, {"date": "2024/09/02", "o": 38.6, "h": 38.6, "l": 37.65, "c": 37.65, "v": 1268188}, {"date": "2024/09/03", "o": 37.75, "h": 38.4, "l": 37.55, "c": 37.75, "v": 1313302}, {"date": "2024/09/04", "o": 35.6, "h": 36.3, "l": 34.85, "c": 35.65, "v": 2106687}, {"date": "2024/09/05", "o": 36.1, "h": 36.4, "l": 35.2, "c": 35.55, "v": 1405302}, {"date": "2024/09/06", "o": 35.55, "h": 36.0, "l": 35.2, "c": 35.8, "v": 987460}, {"date": "2024/09/09", "o": 35.05, "h": 35.6, "l": 34.85, "c": 35.45, "v": 880629}, {"date": "2024/09/10", "o": 35.6, "h": 35.7, "l": 34.3, "c": 34.5, "v": 1658221}, {"date": "2024/09/11", "o": 34.65, "h": 34.85, "l": 34.4, "c": 34.5, "v": 633053}, {"date": "2024/09/12", "o": 35.0, "h": 35.35, "l": 34.85, "c": 35.35, "v": 617442}, {"date": "2024/09/13", "o": 35.6, "h": 35.6, "l": 35.2, "c": 35.45, "v": 582424}, {"date": "2024/09/16", "o": 35.6, "h": 36.2, "l": 35.4, "c": 35.8, "v": 804118}, {"date": "2024/09/18", "o": 35.8, "h": 36.0, "l": 35.1, "c": 35.2, "v": 1126865}, {"date": "2024/09/19", "o": 34.7, "h": 35.3, "l": 34.7, "c": 35.1, "v": 752001}, {"date": "2024/09/20", "o": 35.2, "h": 35.5, "l": 35.0, "c": 35.25, "v": 938543}, {"date": "2024/09/23", "o": 35.35, "h": 35.65, "l": 35.3, "c": 35.3, "v": 702619}, {"date": "2024/09/24", "o": 35.4, "h": 35.7, "l": 34.95, "c": 35.0, "v": 1104829}, {"date": "2024/09/25", "o": 35.3, "h": 35.7, "l": 35.25, "c": 35.45, "v": 858462}, {"date": "2024/09/26", "o": 35.65, "h": 36.2, "l": 35.1, "c": 35.1, "v": 1133654}, {"date": "2024/09/27", "o": 35.4, "h": 35.75, "l": 35.25, "c": 35.55, "v": 740776}, {"date": "2024/09/30", "o": 35.35, "h": 35.8, "l": 35.2, "c": 35.3, "v": 716274}, {"date": "2024/10/01", "o": 35.3, "h": 35.4, "l": 34.8, "c": 35.15, "v": 889513}, {"date": "2024/10/04", "o": 35.3, "h": 35.3, "l": 34.7, "c": 34.7, "v": 755786}, {"date": "2024/10/07", "o": 34.95, "h": 35.2, "l": 34.8, "c": 34.95, "v": 621935}, {"date": "2024/10/08", "o": 34.8, "h": 34.95, "l": 34.2, "c": 34.6, "v": 1156608}, {"date": "2024/10/09", "o": 34.7, "h": 34.9, "l": 33.9, "c": 33.9, "v": 896752}, {"date": "2024/10/11", "o": 34.0, "h": 34.15, "l": 33.75, "c": 33.9, "v": 596515}, {"date": "2024/10/14", "o": 33.9, "h": 34.2, "l": 33.7, "c": 34.0, "v": 539126}, {"date": "2024/10/15", "o": 34.15, "h": 34.45, "l": 33.85, "c": 33.85, "v": 604360}, {"date": "2024/10/16", "o": 33.6, "h": 34.1, "l": 33.55, "c": 33.9, "v": 630230}, {"date": "2024/10/17", "o": 34.1, "h": 35.05, "l": 34.1, "c": 34.8, "v": 1303380}, {"date": "2024/10/18", "o": 35.0, "h": 35.05, "l": 34.3, "c": 34.3, "v": 605010}, {"date": "2024/10/21", "o": 34.7, "h": 35.1, "l": 34.4, "c": 34.9, "v": 920029}, {"date": "2024/10/22", "o": 34.8, "h": 34.9, "l": 34.5, "c": 34.8, "v": 633432}, {"date": "2024/10/23", "o": 34.9, "h": 35.2, "l": 34.7, "c": 34.7, "v": 712498}, {"date": "2024/10/24", "o": 34.85, "h": 34.85, "l": 34.3, "c": 34.4, "v": 825549}, {"date": "2024/10/25", "o": 34.6, "h": 34.75, "l": 34.3, "c": 34.4, "v": 456576}, {"date": "2024/10/28", "o": 34.85, "h": 34.85, "l": 33.75, "c": 34.1, "v": 708070}, {"date": "2024/10/29", "o": 33.9, "h": 33.95, "l": 33.3, "c": 33.45, "v": 861928}, {"date": "2024/10/30", "o": 33.5, "h": 33.75, "l": 33.3, "c": 33.45, "v": 565534}, {"date": "2024/11/01", "o": 33.05, "h": 33.9, "l": 32.8, "c": 33.85, "v": 407414}, {"date": "2024/11/04", "o": 33.95, "h": 34.0, "l": 33.6, "c": 33.75, "v": 389066}, {"date": "2024/11/05", "o": 33.65, "h": 34.2, "l": 33.5, "c": 33.8, "v": 405529}, {"date": "2024/11/06", "o": 34.0, "h": 34.2, "l": 33.9, "c": 33.95, "v": 485360}, {"date": "2024/11/07", "o": 33.9, "h": 34.5, "l": 33.9, "c": 34.45, "v": 566482}, {"date": "2024/11/08", "o": 34.65, "h": 34.65, "l": 33.75, "c": 33.85, "v": 667733}, {"date": "2024/11/11", "o": 33.85, "h": 33.9, "l": 33.45, "c": 33.85, "v": 609324}, {"date": "2024/11/12", "o": 33.6, "h": 33.6, "l": 33.0, "c": 33.1, "v": 973240}, {"date": "2024/11/13", "o": 33.4, "h": 33.4, "l": 33.0, "c": 33.05, "v": 669694}, {"date": "2024/11/14", "o": 33.0, "h": 33.15, "l": 32.15, "c": 32.25, "v": 927080}, {"date": "2024/11/15", "o": 32.35, "h": 33.05, "l": 32.35, "c": 32.65, "v": 433003}, {"date": "2024/11/18", "o": 32.65, "h": 32.9, "l": 32.25, "c": 32.25, "v": 459872}, {"date": "2024/11/19", "o": 32.3, "h": 33.0, "l": 32.3, "c": 32.95, "v": 696510}, {"date": "2024/11/20", "o": 32.6, "h": 32.6, "l": 32.6, "c": 32.6, "v": 675594}, {"date": "2024/11/21", "o": 32.65, "h": 32.65, "l": 32.25, "c": 32.35, "v": 659386}, {"date": "2024/11/22", "o": 32.55, "h": 32.75, "l": 32.5, "c": 32.5, "v": 446400}, {"date": "2024/11/25", "o": 32.45, "h": 32.95, "l": 32.4, "c": 32.85, "v": 638182}, {"date": "2024/11/26", "o": 32.9, "h": 33.04, "l": 32.55, "c": 32.75, "v": 492869}, {"date": "2024/11/27", "o": 32.75, "h": 32.8, "l": 31.86, "c": 31.86, "v": 620052}, {"date": "2024/11/28", "o": 31.86, "h": 31.86, "l": 30.97, "c": 31.46, "v": 1064649}, {"date": "2024/11/29", "o": 31.46, "h": 31.76, "l": 31.27, "c": 31.61, "v": 572096}, {"date": "2024/12/02", "o": 31.86, "h": 32.11, "l": 31.32, "c": 31.32, "v": 651123}, {"date": "2024/12/03", "o": 31.61, "h": 31.96, "l": 31.46, "c": 31.81, "v": 648068}, {"date": "2024/12/04", "o": 31.5, "h": 32.1, "l": 31.5, "c": 31.95, "v": 921221}, {"date": "2024/12/05", "o": 32.2, "h": 32.55, "l": 31.55, "c": 31.55, "v": 871683}, {"date": "2024/12/06", "o": 31.8, "h": 31.9, "l": 31.6, "c": 31.65, "v": 403820}, {"date": "2024/12/09", "o": 31.7, "h": 31.7, "l": 30.9, "c": 31.0, "v": 849197}, {"date": "2024/12/10", "o": 31.0, "h": 31.55, "l": 30.8, "c": 31.0, "v": 584074}, {"date": "2024/12/11", "o": 30.95, "h": 30.95, "l": 30.45, "c": 30.45, "v": 816957}, {"date": "2024/12/12", "o": 30.65, "h": 31.5, "l": 30.65, "c": 30.75, "v": 702800}, {"date": "2024/12/13", "o": 30.65, "h": 30.65, "l": 29.85, "c": 29.85, "v": 1180092}, {"date": "2024/12/16", "o": 29.8, "h": 29.8, "l": 29.15, "c": 29.15, "v": 1600902}, {"date": "2024/12/17", "o": 29.2, "h": 32.05, "l": 29.2, "c": 32.05, "v": 6101724}, {"date": "2024/12/18", "o": 33.15, "h": 33.3, "l": 31.65, "c": 32.6, "v": 12763896}, {"date": "2024/12/19", "o": 31.7, "h": 32.55, "l": 31.6, "c": 32.2, "v": 4437633}, {"date": "2024/12/20", "o": 32.2, "h": 34.4, "l": 32.1, "c": 32.85, "v": 10610586}, {"date": "2024/12/23", "o": 34.5, "h": 36.1, "l": 34.1, "c": 36.1, "v": 12905402}, {"date": "2024/12/24", "o": 39.6, "h": 39.7, "l": 38.5, "c": 39.7, "v": 32788939}, {"date": "2024/12/25", "o": 40.25, "h": 42.8, "l": 39.3, "c": 42.35, "v": 91470439}, {"date": "2024/12/26", "o": 42.35, "h": 42.35, "l": 40.3, "c": 41.2, "v": 28136090}, {"date": "2024/12/27", "o": 41.2, "h": 41.9, "l": 39.75, "c": 40.2, "v": 18454502}, {"date": "2024/12/30", "o": 40.2, "h": 40.75, "l": 37.8, "c": 37.85, "v": 18284599}, {"date": "2024/12/31", "o": 37.7, "h": 39.4, "l": 37.4, "c": 38.15, "v": 25114100}, {"date": "2025/01/02", "o": 38.2, "h": 40.55, "l": 38.15, "c": 39.1, "v": 22343199}, {"date": "2025/01/03", "o": 39.05, "h": 39.1, "l": 37.35, "c": 37.95, "v": 10542684}, {"date": "2025/01/06", "o": 38.8, "h": 38.8, "l": 37.05, "c": 38.0, "v": 9638289}, {"date": "2025/01/07", "o": 39.0, "h": 40.0, "l": 38.25, "c": 38.45, "v": 18345050}, {"date": "2025/01/08", "o": 38.1, "h": 38.5, "l": 37.55, "c": 38.45, "v": 6061512}, {"date": "2025/01/09", "o": 38.45, "h": 38.5, "l": 36.6, "c": 36.6, "v": 8064958}, {"date": "2025/01/10", "o": 36.95, "h": 37.35, "l": 35.7, "c": 36.15, "v": 5314133}, {"date": "2025/01/13", "o": 35.75, "h": 36.0, "l": 34.5, "c": 35.95, "v": 5961162}, {"date": "2025/01/14", "o": 35.8, "h": 36.35, "l": 35.4, "c": 36.3, "v": 3039577}, {"date": "2025/01/15", "o": 36.1, "h": 36.45, "l": 35.4, "c": 35.55, "v": 3290995}, {"date": "2025/01/16", "o": 36.15, "h": 36.5, "l": 35.75, "c": 35.85, "v": 2596550}, {"date": "2025/01/17", "o": 36.0, "h": 36.6, "l": 35.6, "c": 36.0, "v": 3213855}, {"date": "2025/01/20", "o": 36.6, "h": 37.25, "l": 36.0, "c": 37.2, "v": 5739926}, {"date": "2025/01/21", "o": 37.2, "h": 37.3, "l": 36.2, "c": 36.35, "v": 3741665}, {"date": "2025/01/22", "o": 36.85, "h": 36.85, "l": 36.2, "c": 36.8, "v": 2564650}, {"date": "2025/02/03", "o": 35.6, "h": 36.8, "l": 35.3, "c": 36.8, "v": 2766404}, {"date": "2025/02/04", "o": 36.95, "h": 38.9, "l": 36.3, "c": 38.85, "v": 13679084}, {"date": "2025/02/05", "o": 38.5, "h": 40.3, "l": 38.1, "c": 39.95, "v": 16932931}, {"date": "2025/02/06", "o": 40.0, "h": 40.4, "l": 39.2, "c": 39.85, "v": 10824269}, {"date": "2025/02/07", "o": 39.95, "h": 42.15, "l": 39.55, "c": 40.8, "v": 20079280}, {"date": "2025/02/10", "o": 40.5, "h": 41.85, "l": 40.15, "c": 41.2, "v": 10295993}, {"date": "2025/02/11", "o": 40.35, "h": 41.75, "l": 39.5, "c": 40.75, "v": 14885627}, {"date": "2025/02/12", "o": 40.9, "h": 42.2, "l": 40.05, "c": 40.25, "v": 13418914}, {"date": "2025/02/13", "o": 40.9, "h": 40.9, "l": 40.0, "c": 40.2, "v": 5319227}, {"date": "2025/02/14", "o": 40.65, "h": 40.9, "l": 39.4, "c": 39.45, "v": 6089501}, {"date": "2025/02/17", "o": 40.15, "h": 42.95, "l": 40.05, "c": 42.0, "v": 25902405}, {"date": "2025/02/18", "o": 41.9, "h": 42.6, "l": 41.35, "c": 41.4, "v": 11924386}, {"date": "2025/02/19", "o": 42.0, "h": 42.7, "l": 41.0, "c": 41.05, "v": 9974315}, {"date": "2025/02/20", "o": 41.2, "h": 41.45, "l": 40.55, "c": 40.95, "v": 3878334}, {"date": "2025/02/21", "o": 41.3, "h": 41.5, "l": 40.8, "c": 40.95, "v": 4039183}, {"date": "2025/02/24", "o": 40.8, "h": 45.0, "l": 40.45, "c": 45.0, "v": 43305373}, {"date": "2025/02/25", "o": 45.65, "h": 49.5, "l": 45.5, "c": 49.1, "v": 116508335}, {"date": "2025/02/26", "o": 49.5, "h": 50.6, "l": 48.0, "c": 48.0, "v": 92449035}, {"date": "2025/02/27", "o": 48.45, "h": 52.7, "l": 48.25, "c": 48.3, "v": 84954665}, {"date": "2025/03/03", "o": 48.45, "h": 50.1, "l": 46.8, "c": 47.15, "v": 50252750}, {"date": "2025/03/04", "o": 46.3, "h": 49.3, "l": 46.05, "c": 47.35, "v": 28918145}, {"date": "2025/03/05", "o": 48.0, "h": 48.3, "l": 46.1, "c": 46.95, "v": 27667309}, {"date": "2025/03/06", "o": 46.7, "h": 47.3, "l": 45.05, "c": 45.3, "v": 17019213}, {"date": "2025/03/07", "o": 45.1, "h": 45.7, "l": 43.7, "c": 43.85, "v": 16458962}, {"date": "2025/03/10", "o": 44.1, "h": 44.25, "l": 42.3, "c": 42.6, "v": 10901964}, {"date": "2025/03/11", "o": 41.65, "h": 43.2, "l": 41.25, "c": 42.7, "v": 15884147}, {"date": "2025/03/12", "o": 42.85, "h": 43.4, "l": 42.3, "c": 42.75, "v": 8368260}, {"date": "2025/03/13", "o": 43.4, "h": 44.35, "l": 41.65, "c": 41.7, "v": 13963304}, {"date": "2025/03/14", "o": 41.9, "h": 43.0, "l": 41.3, "c": 42.65, "v": 7682128}, {"date": "2025/03/17", "o": 43.2, "h": 44.65, "l": 42.7, "c": 44.1, "v": 17225552}, {"date": "2025/03/18", "o": 44.1, "h": 44.15, "l": 43.25, "c": 43.6, "v": 14705987}, {"date": "2025/03/19", "o": 43.7, "h": 43.8, "l": 42.1, "c": 42.4, "v": 8337554}, {"date": "2025/03/20", "o": 42.8, "h": 43.9, "l": 42.8, "c": 43.3, "v": 7494235}, {"date": "2025/03/21", "o": 43.5, "h": 43.95, "l": 42.65, "c": 43.95, "v": 11263274}, {"date": "2025/03/24", "o": 44.0, "h": 44.15, "l": 42.5, "c": 42.95, "v": 7936597}, {"date": "2025/03/25", "o": 43.25, "h": 43.95, "l": 42.0, "c": 42.15, "v": 6839810}, {"date": "2025/03/26", "o": 42.5, "h": 43.2, "l": 42.5, "c": 42.7, "v": 5329155}, {"date": "2025/03/27", "o": 42.3, "h": 42.65, "l": 41.9, "c": 42.6, "v": 3951273}, {"date": "2025/03/28", "o": 42.15, "h": 42.25, "l": 39.75, "c": 40.25, "v": 8478068}, {"date": "2025/03/31", "o": 38.6, "h": 39.55, "l": 37.6, "c": 37.7, "v": 7178272}, {"date": "2025/04/01", "o": 38.5, "h": 38.7, "l": 38.1, "c": 38.2, "v": 3090514}, {"date": "2025/04/02", "o": 38.3, "h": 39.0, "l": 37.6, "c": 39.0, "v": 3530652}, {"date": "2025/04/07", "o": 35.1, "h": 35.1, "l": 35.1, "c": 35.1, "v": 339550}, {"date": "2025/04/08", "o": 31.6, "h": 31.8, "l": 31.6, "c": 31.6, "v": 2977302}, {"date": "2025/04/09", "o": 29.4, "h": 30.3, "l": 28.45, "c": 28.45, "v": 9216227}, {"date": "2025/04/10", "o": 31.25, "h": 31.25, "l": 31.25, "c": 31.25, "v": 1260258}, {"date": "2025/04/11", "o": 30.5, "h": 32.2, "l": 29.2, "c": 32.15, "v": 5779224}, {"date": "2025/04/14", "o": 32.55, "h": 34.15, "l": 32.5, "c": 32.65, "v": 4091540}, {"date": "2025/04/15", "o": 33.0, "h": 34.75, "l": 33.0, "c": 34.6, "v": 4140470}, {"date": "2025/04/16", "o": 34.1, "h": 34.7, "l": 33.6, "c": 33.6, "v": 2840912}, {"date": "2025/04/17", "o": 33.4, "h": 33.95, "l": 32.8, "c": 33.3, "v": 2204190}, {"date": "2025/04/18", "o": 33.5, "h": 33.95, "l": 33.35, "c": 33.65, "v": 1728346}, {"date": "2025/04/21", "o": 33.9, "h": 34.05, "l": 32.35, "c": 32.55, "v": 2081324}, {"date": "2025/04/22", "o": 31.7, "h": 32.85, "l": 31.7, "c": 31.9, "v": 2342455}, {"date": "2025/04/23", "o": 32.95, "h": 33.9, "l": 32.95, "c": 33.6, "v": 2844211}, {"date": "2025/04/24", "o": 34.1, "h": 34.15, "l": 33.35, "c": 33.4, "v": 2477942}, {"date": "2025/04/25", "o": 34.2, "h": 34.65, "l": 33.75, "c": 34.05, "v": 2463505}, {"date": "2025/04/28", "o": 34.45, "h": 34.65, "l": 34.15, "c": 34.4, "v": 1827229}, {"date": "2025/04/29", "o": 35.8, "h": 36.0, "l": 34.9, "c": 35.45, "v": 8555633}, {"date": "2025/04/30", "o": 35.65, "h": 37.45, "l": 35.3, "c": 36.3, "v": 13641453}, {"date": "2025/05/02", "o": 36.9, "h": 36.95, "l": 36.0, "c": 36.4, "v": 7349258}, {"date": "2025/05/05", "o": 36.6, "h": 36.65, "l": 33.2, "c": 34.1, "v": 6312176}, {"date": "2025/05/06", "o": 34.2, "h": 34.7, "l": 33.95, "c": 34.5, "v": 2052310}, {"date": "2025/05/07", "o": 34.75, "h": 34.9, "l": 34.0, "c": 34.6, "v": 1952600}, {"date": "2025/05/08", "o": 34.95, "h": 35.6, "l": 34.85, "c": 35.45, "v": 2293761}, {"date": "2025/05/09", "o": 35.5, "h": 36.2, "l": 34.85, "c": 36.1, "v": 4546304}, {"date": "2025/05/12", "o": 36.35, "h": 37.65, "l": 36.35, "c": 37.5, "v": 10257733}, {"date": "2025/05/13", "o": 38.35, "h": 38.45, "l": 37.15, "c": 37.95, "v": 8130473}, {"date": "2025/05/14", "o": 39.1, "h": 41.2, "l": 38.95, "c": 40.25, "v": 20287637}, {"date": "2025/05/15", "o": 40.3, "h": 42.15, "l": 39.75, "c": 41.45, "v": 15540743}, {"date": "2025/05/16", "o": 41.3, "h": 41.9, "l": 40.75, "c": 41.45, "v": 8871321}, {"date": "2025/05/19", "o": 41.45, "h": 42.0, "l": 40.2, "c": 40.45, "v": 9344443}, {"date": "2025/05/20", "o": 40.8, "h": 41.5, "l": 39.85, "c": 40.3, "v": 5673462}, {"date": "2025/05/21", "o": 40.7, "h": 40.8, "l": 39.95, "c": 40.3, "v": 2644294}, {"date": "2025/05/22", "o": 40.1, "h": 40.95, "l": 39.8, "c": 40.6, "v": 3883215}, {"date": "2025/05/23", "o": 41.05, "h": 41.3, "l": 40.05, "c": 40.15, "v": 3821764}, {"date": "2025/05/26", "o": 40.15, "h": 41.2, "l": 39.9, "c": 40.8, "v": 4005594}, {"date": "2025/05/27", "o": 40.85, "h": 41.85, "l": 40.75, "c": 40.9, "v": 11378404}, {"date": "2025/05/28", "o": 41.45, "h": 41.95, "l": 40.6, "c": 40.75, "v": 8482792}, {"date": "2025/05/29", "o": 41.2, "h": 41.25, "l": 40.2, "c": 40.35, "v": 3285314}, {"date": "2025/06/02", "o": 40.15, "h": 40.15, "l": 39.0, "c": 39.4, "v": 3366108}, {"date": "2025/06/03", "o": 39.8, "h": 40.0, "l": 38.5, "c": 38.6, "v": 3765873}, {"date": "2025/06/04", "o": 39.3, "h": 40.65, "l": 39.3, "c": 40.65, "v": 5169767}, {"date": "2025/06/05", "o": 40.65, "h": 41.1, "l": 39.7, "c": 39.75, "v": 4147861}, {"date": "2025/06/06", "o": 39.8, "h": 39.95, "l": 39.15, "c": 39.15, "v": 1929389}, {"date": "2025/06/09", "o": 39.4, "h": 39.5, "l": 38.55, "c": 38.9, "v": 1907569}, {"date": "2025/06/10", "o": 39.25, "h": 40.2, "l": 39.25, "c": 39.75, "v": 3706530}, {"date": "2025/06/11", "o": 41.1, "h": 41.9, "l": 40.35, "c": 41.1, "v": 13460288}, {"date": "2025/06/12", "o": 41.5, "h": 42.15, "l": 41.0, "c": 41.1, "v": 9384974}, {"date": "2025/06/13", "o": 41.0, "h": 41.0, "l": 39.3, "c": 39.3, "v": 6364032}, {"date": "2025/06/16", "o": 39.3, "h": 39.7, "l": 38.85, "c": 39.7, "v": 1915107}, {"date": "2025/06/17", "o": 40.0, "h": 40.35, "l": 39.6, "c": 39.8, "v": 2565245}, {"date": "2025/06/18", "o": 39.95, "h": 40.2, "l": 39.6, "c": 39.8, "v": 2043645}, {"date": "2025/06/19", "o": 39.8, "h": 40.0, "l": 38.7, "c": 38.85, "v": 2649340}, {"date": "2025/06/20", "o": 38.85, "h": 39.5, "l": 38.1, "c": 38.75, "v": 2457938}, {"date": "2025/06/23", "o": 38.0, "h": 38.8, "l": 37.5, "c": 38.7, "v": 1900238}, {"date": "2025/06/24", "o": 39.35, "h": 40.45, "l": 39.35, "c": 40.15, "v": 3662138}, {"date": "2025/06/25", "o": 40.3, "h": 40.65, "l": 39.8, "c": 39.85, "v": 1787742}, {"date": "2025/06/26", "o": 40.05, "h": 41.0, "l": 40.05, "c": 40.1, "v": 3061155}, {"date": "2025/06/27", "o": 40.7, "h": 40.7, "l": 39.85, "c": 39.95, "v": 1522469}, {"date": "2025/06/30", "o": 40.15, "h": 40.45, "l": 39.3, "c": 39.35, "v": 1458367}, {"date": "2025/07/01", "o": 39.7, "h": 39.95, "l": 39.3, "c": 39.35, "v": 1188929}, {"date": "2025/07/02", "o": 39.45, "h": 40.0, "l": 39.45, "c": 40.0, "v": 1336427}, {"date": "2025/07/03", "o": 40.9, "h": 40.9, "l": 40.2, "c": 40.3, "v": 3164900}, {"date": "2025/07/04", "o": 40.7, "h": 40.9, "l": 38.35, "c": 38.45, "v": 4537466}, {"date": "2025/07/07", "o": 38.5, "h": 38.5, "l": 37.6, "c": 38.25, "v": 1382469}, {"date": "2025/07/08", "o": 38.1, "h": 38.15, "l": 37.25, "c": 37.75, "v": 1962571}, {"date": "2025/07/09", "o": 37.8, "h": 38.15, "l": 37.5, "c": 38.0, "v": 1000000}, {"date": "2025/07/10", "o": 38.25, "h": 39.45, "l": 38.05, "c": 39.0, "v": 4778500}, {"date": "2025/07/11", "o": 38.75, "h": 39.5, "l": 38.5, "c": 38.95, "v": 2651421}, {"date": "2025/07/14", "o": 38.8, "h": 38.9, "l": 38.0, "c": 38.0, "v": 1917215}, {"date": "2025/07/15", "o": 38.0, "h": 38.4, "l": 37.9, "c": 38.25, "v": 1425284}, {"date": "2025/07/16", "o": 38.25, "h": 38.8, "l": 38.2, "c": 38.35, "v": 1258090}, {"date": "2025/07/17", "o": 38.7, "h": 39.6, "l": 38.6, "c": 39.5, "v": 3159702}, {"date": "2025/07/18", "o": 39.6, "h": 40.4, "l": 39.5, "c": 39.7, "v": 3147087}, {"date": "2025/07/21", "o": 40.3, "h": 41.1, "l": 40.05, "c": 40.05, "v": 6072240}, {"date": "2025/07/22", "o": 40.45, "h": 40.55, "l": 38.2, "c": 38.45, "v": 3687467}, {"date": "2025/07/23", "o": 38.8, "h": 40.1, "l": 38.75, "c": 39.85, "v": 3997605}, {"date": "2025/07/24", "o": 40.5, "h": 40.8, "l": 39.5, "c": 40.5, "v": 4223111}, {"date": "2025/07/25", "o": 40.6, "h": 40.6, "l": 39.35, "c": 39.35, "v": 2616098}, {"date": "2025/07/28", "o": 39.65, "h": 40.0, "l": 39.3, "c": 39.8, "v": 1505348}, {"date": "2025/07/29", "o": 39.8, "h": 40.2, "l": 39.25, "c": 39.8, "v": 1560370}, {"date": "2025/07/30", "o": 39.75, "h": 40.55, "l": 39.2, "c": 40.4, "v": 3185281}, {"date": "2025/07/31", "o": 41.55, "h": 41.55, "l": 39.85, "c": 40.5, "v": 7250897}, {"date": "2025/08/04", "o": 40.5, "h": 41.5, "l": 39.95, "c": 41.25, "v": 5172503}, {"date": "2025/08/05", "o": 41.7, "h": 45.35, "l": 41.5, "c": 45.35, "v": 33597899}, {"date": "2025/08/06", "o": 45.95, "h": 46.15, "l": 43.35, "c": 43.6, "v": 49140350}, {"date": "2025/08/07", "o": 43.6, "h": 43.9, "l": 41.15, "c": 41.2, "v": 18193405}, {"date": "2025/08/08", "o": 41.5, "h": 43.15, "l": 41.1, "c": 42.4, "v": 13552258}, {"date": "2025/08/11", "o": 42.2, "h": 44.25, "l": 42.15, "c": 44.1, "v": 16097973}, {"date": "2025/08/12", "o": 44.55, "h": 44.55, "l": 43.5, "c": 44.0, "v": 10027149}, {"date": "2025/08/13", "o": 44.35, "h": 45.8, "l": 43.4, "c": 44.6, "v": 23112135}, {"date": "2025/08/14", "o": 45.6, "h": 45.9, "l": 44.6, "c": 44.9, "v": 15048563}, {"date": "2025/08/15", "o": 45.5, "h": 47.55, "l": 44.6, "c": 46.7, "v": 22592689}, {"date": "2025/08/18", "o": 47.95, "h": 49.8, "l": 46.85, "c": 47.2, "v": 27051047}, {"date": "2025/08/19", "o": 47.55, "h": 48.9, "l": 46.05, "c": 47.55, "v": 16314238}, {"date": "2025/08/20", "o": 48.0, "h": 48.65, "l": 45.8, "c": 46.45, "v": 28190362}, {"date": "2025/08/21", "o": 47.0, "h": 51.0, "l": 47.0, "c": 51.0, "v": 56186747}, {"date": "2025/08/22", "o": 51.3, "h": 51.3, "l": 47.1, "c": 47.5, "v": 43163434}, {"date": "2025/08/25", "o": 49.1, "h": 52.2, "l": 48.6, "c": 52.2, "v": 49215338}, {"date": "2025/08/26", "o": 52.8, "h": 54.0, "l": 51.1, "c": 52.2, "v": 48318651}, {"date": "2025/08/27", "o": 52.6, "h": 52.9, "l": 50.6, "c": 51.5, "v": 22369290}, {"date": "2025/08/28", "o": 51.6, "h": 51.7, "l": 49.45, "c": 50.3, "v": 16443618}, {"date": "2025/08/29", "o": 51.0, "h": 51.1, "l": 49.7, "c": 50.3, "v": 10315098}, {"date": "2025/09/01", "o": 50.6, "h": 52.5, "l": 49.05, "c": 51.3, "v": 32911013}, {"date": "2025/09/02", "o": 52.4, "h": 53.2, "l": 50.2, "c": 50.8, "v": 29188688}, {"date": "2025/09/03", "o": 51.9, "h": 55.0, "l": 50.8, "c": 54.2, "v": 44584701}, {"date": "2025/09/04", "o": 54.3, "h": 55.5, "l": 52.1, "c": 53.8, "v": 32509991}, {"date": "2025/09/05", "o": 54.6, "h": 59.1, "l": 54.3, "c": 59.1, "v": 54998342}, {"date": "2025/09/08", "o": 60.0, "h": 64.9, "l": 57.4, "c": 63.0, "v": 78284355}, {"date": "2025/09/09", "o": 63.4, "h": 63.5, "l": 61.0, "c": 62.2, "v": 26856017}, {"date": "2025/09/10", "o": 62.7, "h": 62.7, "l": 60.3, "c": 61.4, "v": 23659988}, {"date": "2025/09/11", "o": 61.7, "h": 62.4, "l": 56.8, "c": 57.1, "v": 35909250}, {"date": "2025/09/12", "o": 58.0, "h": 59.6, "l": 56.8, "c": 58.8, "v": 31677249}, {"date": "2025/09/15", "o": 58.1, "h": 58.3, "l": 55.4, "c": 55.7, "v": 19731590}, {"date": "2025/09/16", "o": 56.2, "h": 58.4, "l": 54.3, "c": 55.2, "v": 27085524}, {"date": "2025/09/17", "o": 55.3, "h": 55.9, "l": 54.8, "c": 55.5, "v": 8917301}, {"date": "2025/09/18", "o": 56.0, "h": 56.6, "l": 52.6, "c": 53.1, "v": 22892571}, {"date": "2025/09/19", "o": 54.3, "h": 54.4, "l": 53.0, "c": 53.4, "v": 10310173}, {"date": "2025/09/22", "o": 53.8, "h": 54.4, "l": 52.5, "c": 53.4, "v": 8899465}, {"date": "2025/09/23", "o": 53.7, "h": 54.3, "l": 52.7, "c": 52.8, "v": 8643147}, {"date": "2025/09/24", "o": 52.8, "h": 53.6, "l": 52.2, "c": 52.7, "v": 6765771}, {"date": "2025/09/25", "o": 53.0, "h": 54.2, "l": 52.7, "c": 52.8, "v": 8275187}, {"date": "2025/09/26", "o": 52.4, "h": 52.5, "l": 50.4, "c": 51.1, "v": 7886690}, {"date": "2025/09/30", "o": 51.5, "h": 52.0, "l": 50.8, "c": 52.0, "v": 4198096}, {"date": "2025/10/01", "o": 52.2, "h": 52.9, "l": 51.0, "c": 51.1, "v": 5674498}, {"date": "2025/10/02", "o": 51.6, "h": 51.6, "l": 50.5, "c": 50.7, "v": 4451181}, {"date": "2025/10/03", "o": 51.2, "h": 51.5, "l": 50.8, "c": 50.9, "v": 3579034}, {"date": "2025/10/07", "o": 51.4, "h": 51.7, "l": 50.9, "c": 51.2, "v": 3169327}, {"date": "2025/10/08", "o": 51.0, "h": 51.9, "l": 50.6, "c": 51.2, "v": 4150397}, {"date": "2025/10/09", "o": 51.3, "h": 51.6, "l": 50.1, "c": 50.3, "v": 4354094}, {"date": "2025/10/13", "o": 46.65, "h": 50.2, "l": 46.6, "c": 49.9, "v": 5042292}, {"date": "2025/10/14", "o": 50.5, "h": 51.0, "l": 48.0, "c": 48.0, "v": 5344474}, {"date": "2025/10/15", "o": 48.6, "h": 48.7, "l": 47.6, "c": 47.8, "v": 3857158}, {"date": "2025/10/16", "o": 48.3, "h": 48.55, "l": 47.8, "c": 48.25, "v": 3276045}, {"date": "2025/10/17", "o": 47.9, "h": 48.4, "l": 47.1, "c": 47.2, "v": 3388062}, {"date": "2025/10/20", "o": 47.5, "h": 48.45, "l": 47.0, "c": 48.3, "v": 4426697}, {"date": "2025/10/21", "o": 48.35, "h": 50.0, "l": 48.35, "c": 49.05, "v": 6615632}, {"date": "2025/10/22", "o": 48.9, "h": 50.7, "l": 48.65, "c": 50.0, "v": 7802434}, {"date": "2025/10/23", "o": 49.75, "h": 49.8, "l": 48.9, "c": 49.15, "v": 2884209}, {"date": "2025/10/27", "o": 49.95, "h": 50.1, "l": 49.3, "c": 49.8, "v": 2883395}, {"date": "2025/10/28", "o": 51.0, "h": 51.5, "l": 49.05, "c": 49.15, "v": 9146525}, {"date": "2025/10/29", "o": 49.8, "h": 50.6, "l": 49.55, "c": 50.2, "v": 5611564}, {"date": "2025/10/30", "o": 49.8, "h": 50.6, "l": 49.05, "c": 49.4, "v": 3822743}, {"date": "2025/10/31", "o": 48.9, "h": 50.2, "l": 48.85, "c": 49.65, "v": 2638500}, {"date": "2025/11/03", "o": 49.8, "h": 50.6, "l": 49.4, "c": 50.3, "v": 3609214}, {"date": "2025/11/04", "o": 48.4, "h": 48.4, "l": 45.3, "c": 45.3, "v": 18426917}, {"date": "2025/11/05", "o": 43.9, "h": 45.25, "l": 43.7, "c": 44.65, "v": 5708834}, {"date": "2025/11/06", "o": 45.05, "h": 45.3, "l": 44.35, "c": 44.7, "v": 3141776}, {"date": "2025/11/07", "o": 44.6, "h": 44.7, "l": 43.85, "c": 44.25, "v": 2906381}, {"date": "2025/11/10", "o": 44.45, "h": 45.3, "l": 44.3, "c": 44.55, "v": 2977405}, {"date": "2025/11/11", "o": 44.8, "h": 45.1, "l": 43.55, "c": 43.6, "v": 4756487}, {"date": "2025/11/12", "o": 43.6, "h": 44.3, "l": 43.6, "c": 43.9, "v": 2809620}, {"date": "2025/11/13", "o": 44.0, "h": 44.15, "l": 43.15, "c": 43.2, "v": 3692656}, {"date": "2025/11/14", "o": 42.6, "h": 43.35, "l": 42.3, "c": 42.3, "v": 2718952}, {"date": "2025/11/17", "o": 42.85, "h": 42.9, "l": 41.85, "c": 41.9, "v": 1962846}, {"date": "2025/11/18", "o": 41.7, "h": 42.15, "l": 40.8, "c": 40.85, "v": 2768445}, {"date": "2025/11/19", "o": 40.85, "h": 41.45, "l": 40.7, "c": 41.15, "v": 1742238}, {"date": "2025/11/20", "o": 42.1, "h": 42.8, "l": 42.05, "c": 42.5, "v": 2565069}, {"date": "2025/11/21", "o": 41.7, "h": 42.4, "l": 41.1, "c": 41.5, "v": 2230691}, {"date": "2025/11/24", "o": 42.0, "h": 42.1, "l": 41.35, "c": 41.85, "v": 1220890}, {"date": "2025/11/25", "o": 42.5, "h": 42.9, "l": 42.35, "c": 42.55, "v": 1866082}, {"date": "2025/11/26", "o": 43.2, "h": 44.35, "l": 43.15, "c": 44.05, "v": 4365229}, {"date": "2025/11/27", "o": 44.5, "h": 44.55, "l": 43.5, "c": 43.55, "v": 2146371}, {"date": "2025/11/28", "o": 43.85, "h": 43.85, "l": 43.2, "c": 43.45, "v": 1433262}, {"date": "2025/12/01", "o": 43.8, "h": 43.85, "l": 42.7, "c": 42.7, "v": 1430518}, {"date": "2025/12/02", "o": 43.0, "h": 43.1, "l": 42.25, "c": 42.25, "v": 1202750}, {"date": "2025/12/03", "o": 42.75, "h": 43.05, "l": 42.45, "c": 42.9, "v": 1477553}, {"date": "2025/12/04", "o": 43.45, "h": 44.3, "l": 43.2, "c": 43.8, "v": 4389760}, {"date": "2025/12/05", "o": 44.65, "h": 45.2, "l": 42.6, "c": 42.8, "v": 12186781}, {"date": "2025/12/08", "o": 42.8, "h": 43.25, "l": 42.25, "c": 43.05, "v": 2341239}, {"date": "2025/12/09", "o": 43.05, "h": 43.05, "l": 42.5, "c": 42.5, "v": 1143320}, {"date": "2025/12/10", "o": 42.85, "h": 43.05, "l": 42.35, "c": 42.35, "v": 1366282}, {"date": "2025/12/11", "o": 42.5, "h": 42.65, "l": 41.65, "c": 41.65, "v": 1752815}, {"date": "2025/12/12", "o": 41.95, "h": 42.4, "l": 41.65, "c": 41.65, "v": 1310950}, {"date": "2025/12/15", "o": 41.0, "h": 41.65, "l": 40.85, "c": 41.35, "v": 1082069}, {"date": "2025/12/16", "o": 41.4, "h": 41.4, "l": 40.35, "c": 40.7, "v": 1843975}, {"date": "2025/12/17", "o": 41.0, "h": 41.9, "l": 41.0, "c": 41.2, "v": 1338524}, {"date": "2025/12/18", "o": 41.1, "h": 41.2, "l": 40.25, "c": 40.25, "v": 1922734}, {"date": "2025/12/19", "o": 40.5, "h": 40.85, "l": 40.35, "c": 40.45, "v": 1288462}, {"date": "2025/12/22", "o": 41.0, "h": 41.35, "l": 41.0, "c": 41.2, "v": 1345780}, {"date": "2025/12/23", "o": 41.35, "h": 41.6, "l": 40.9, "c": 41.1, "v": 1434080}, {"date": "2025/12/24", "o": 41.45, "h": 41.6, "l": 40.5, "c": 40.55, "v": 1520265}, {"date": "2025/12/26", "o": 40.7, "h": 40.85, "l": 40.1, "c": 40.6, "v": 1523101}, {"date": "2025/12/29", "o": 40.8, "h": 41.65, "l": 40.8, "c": 41.2, "v": 1832711}, {"date": "2025/12/30", "o": 41.45, "h": 41.45, "l": 40.15, "c": 40.65, "v": 2064287}, {"date": "2025/12/31", "o": 40.65, "h": 40.95, "l": 40.35, "c": 40.35, "v": 1332723}, {"date": "2026/01/02", "o": 40.85, "h": 41.7, "l": 40.8, "c": 41.05, "v": 2733634}, {"date": "2026/01/05", "o": 41.6, "h": 41.6, "l": 40.35, "c": 40.45, "v": 2502493}, {"date": "2026/01/06", "o": 40.5, "h": 41.3, "l": 40.5, "c": 41.05, "v": 2171148}, {"date": "2026/01/07", "o": 41.15, "h": 41.3, "l": 40.65, "c": 41.0, "v": 1914175}, {"date": "2026/01/08", "o": 41.05, "h": 41.1, "l": 40.2, "c": 40.2, "v": 2418581}, {"date": "2026/01/09", "o": 40.2, "h": 40.65, "l": 39.6, "c": 40.45, "v": 1980179}, {"date": "2026/01/12", "o": 40.1, "h": 40.1, "l": 39.2, "c": 39.6, "v": 4510678}, {"date": "2026/01/13", "o": 39.75, "h": 39.85, "l": 38.7, "c": 39.0, "v": 3575969}, {"date": "2026/01/14", "o": 39.15, "h": 40.85, "l": 39.15, "c": 40.5, "v": 3917788}, {"date": "2026/01/15", "o": 40.7, "h": 40.75, "l": 39.85, "c": 40.2, "v": 1741664}, {"date": "2026/01/16", "o": 40.45, "h": 40.85, "l": 40.1, "c": 40.15, "v": 1948455}, {"date": "2026/01/19", "o": 40.3, "h": 40.95, "l": 39.85, "c": 40.25, "v": 2261575}, {"date": "2026/01/20", "o": 40.25, "h": 41.4, "l": 39.9, "c": 40.95, "v": 3273000}, {"date": "2026/01/21", "o": 40.85, "h": 43.6, "l": 40.25, "c": 43.35, "v": 17390930}, {"date": "2026/01/22", "o": 45.35, "h": 45.4, "l": 43.7, "c": 44.95, "v": 31777386}, {"date": "2026/01/23", "o": 44.55, "h": 44.6, "l": 43.0, "c": 43.15, "v": 10123406}, {"date": "2026/01/26", "o": 42.85, "h": 43.65, "l": 42.35, "c": 42.85, "v": 5930218}, {"date": "2026/01/27", "o": 42.6, "h": 42.75, "l": 41.4, "c": 41.4, "v": 5425878}, {"date": "2026/01/28", "o": 41.6, "h": 41.95, "l": 40.9, "c": 41.95, "v": 4532926}, {"date": "2026/01/29", "o": 42.25, "h": 43.15, "l": 40.5, "c": 40.5, "v": 7886256}, {"date": "2026/01/30", "o": 40.8, "h": 40.8, "l": 38.85, "c": 39.1, "v": 4849721}, {"date": "2026/02/02", "o": 38.15, "h": 38.5, "l": 37.55, "c": 37.8, "v": 4136285}, {"date": "2026/02/03", "o": 38.3, "h": 38.6, "l": 37.75, "c": 38.25, "v": 2232531}, {"date": "2026/02/04", "o": 38.5, "h": 39.4, "l": 38.5, "c": 39.0, "v": 2138995}, {"date": "2026/02/05", "o": 38.95, "h": 39.3, "l": 38.25, "c": 38.4, "v": 1507999}, {"date": "2026/02/06", "o": 38.05, "h": 38.05, "l": 37.05, "c": 37.45, "v": 1973604}, {"date": "2026/02/09", "o": 38.2, "h": 38.9, "l": 37.8, "c": 37.8, "v": 1331354}, {"date": "2026/02/10", "o": 38.05, "h": 38.2, "l": 37.65, "c": 37.85, "v": 1143668}, {"date": "2026/02/11", "o": 38.25, "h": 38.55, "l": 37.8, "c": 38.4, "v": 1715670}, {"date": "2026/02/23", "o": 38.7, "h": 40.1, "l": 38.65, "c": 40.1, "v": 2457056}, {"date": "2026/02/24", "o": 39.75, "h": 40.65, "l": 39.2, "c": 40.4, "v": 3970253}, {"date": "2026/02/25", "o": 40.55, "h": 40.7, "l": 39.6, "c": 39.75, "v": 2488924}, {"date": "2026/02/26", "o": 40.0, "h": 40.2, "l": 39.75, "c": 39.75, "v": 1673488}, {"date": "2026/03/02", "o": 38.55, "h": 40.15, "l": 38.55, "c": 40.0, "v": 2135183}, {"date": "2026/03/03", "o": 40.2, "h": 40.25, "l": 38.5, "c": 38.7, "v": 2536227}, {"date": "2026/03/04", "o": 37.55, "h": 38.05, "l": 36.5, "c": 36.8, "v": 2508371}, {"date": "2026/03/05", "o": 37.7, "h": 38.25, "l": 37.6, "c": 38.0, "v": 1562806}, {"date": "2026/03/06", "o": 37.85, "h": 38.2, "l": 37.25, "c": 38.1, "v": 1000370}, {"date": "2026/03/09", "o": 36.2, "h": 36.8, "l": 35.0, "c": 36.35, "v": 2078244}, {"date": "2026/03/10", "o": 37.1, "h": 37.35, "l": 36.75, "c": 37.0, "v": 1040945}, {"date": "2026/03/11", "o": 37.5, "h": 38.2, "l": 37.45, "c": 38.1, "v": 1466841}, {"date": "2026/03/12", "o": 37.9, "h": 38.25, "l": 37.2, "c": 37.5, "v": 1244001}, {"date": "2026/03/13", "o": 37.25, "h": 37.75, "l": 36.9, "c": 37.45, "v": 1039279}, {"date": "2026/03/16", "o": 37.7, "h": 38.45, "l": 37.7, "c": 38.45, "v": 1483389}, {"date": "2026/03/17", "o": 38.7, "h": 39.15, "l": 38.45, "c": 38.6, "v": 1524048}, {"date": "2026/03/18", "o": 39.15, "h": 39.15, "l": 38.05, "c": 38.3, "v": 1263302}, {"date": "2026/03/19", "o": 38.2, "h": 38.5, "l": 37.85, "c": 37.85, "v": 1393409}, {"date": "2026/03/20", "o": 38.2, "h": 38.45, "l": 37.7, "c": 37.95, "v": 1149001}, {"date": "2026/03/23", "o": 37.1, "h": 38.15, "l": 36.7, "c": 37.25, "v": 1215358}, {"date": "2026/03/24", "o": 37.95, "h": 38.1, "l": 36.7, "c": 36.85, "v": 1021841}, {"date": "2026/03/25", "o": 37.5, "h": 37.75, "l": 37.35, "c": 37.4, "v": 804020}, {"date": "2026/03/26", "o": 37.5, "h": 37.9, "l": 36.75, "c": 36.75, "v": 1483346}, {"date": "2026/03/27", "o": 36.75, "h": 36.95, "l": 36.2, "c": 36.95, "v": 1130612}, {"date": "2026/03/30", "o": 36.3, "h": 36.65, "l": 36.0, "c": 36.1, "v": 1135748}, {"date": "2026/03/31", "o": 36.0, "h": 36.35, "l": 35.0, "c": 35.1, "v": 1715707}, {"date": "2026/04/01", "o": 36.0, "h": 36.4, "l": 35.85, "c": 36.1, "v": 1080914}, {"date": "2026/04/02", "o": 36.5, "h": 36.5, "l": 35.4, "c": 35.4, "v": 888060}, {"date": "2026/04/07", "o": 35.65, "h": 36.1, "l": 35.55, "c": 36.0, "v": 778569}, {"date": "2026/04/08", "o": 36.5, "h": 37.2, "l": 36.5, "c": 37.15, "v": 1338765}, {"date": "2026/04/09", "o": 37.2, "h": 37.25, "l": 36.15, "c": 36.35, "v": 1311304}, {"date": "2026/04/10", "o": 36.5, "h": 36.85, "l": 36.4, "c": 36.65, "v": 844874}, {"date": "2026/04/13", "o": 36.55, "h": 36.55, "l": 36.05, "c": 36.3, "v": 1219855}, {"date": "2026/04/14", "o": 36.8, "h": 37.05, "l": 36.6, "c": 36.9, "v": 1589681}, {"date": "2026/04/15", "o": 37.2, "h": 37.45, "l": 36.6, "c": 36.6, "v": 1832959}, {"date": "2026/04/16", "o": 36.8, "h": 37.5, "l": 36.8, "c": 37.1, "v": 1511629}, {"date": "2026/04/17", "o": 37.3, "h": 37.8, "l": 37.25, "c": 37.65, "v": 2489115}, {"date": "2026/04/20", "o": 37.8, "h": 38.2, "l": 37.2, "c": 37.2, "v": 2083963}, {"date": "2026/04/21", "o": 37.3, "h": 38.15, "l": 37.3, "c": 38.1, "v": 1867467}, {"date": "2026/04/22", "o": 38.5, "h": 39.4, "l": 38.15, "c": 38.6, "v": 3554681}, {"date": "2026/04/23", "o": 39.0, "h": 39.0, "l": 35.95, "c": 36.65, "v": 3543565}, {"date": "2026/04/24", "o": 36.9, "h": 40.25, "l": 36.8, "c": 38.5, "v": 9900480}, {"date": "2026/04/27", "o": 39.0, "h": 39.15, "l": 37.3, "c": 38.7, "v": 5720929}, {"date": "2026/04/28", "o": 38.95, "h": 40.25, "l": 37.9, "c": 40.2, "v": 8954303}, {"date": "2026/04/29", "o": 40.05, "h": 41.4, "l": 39.6, "c": 40.8, "v": 7910285}, {"date": "2026/04/30", "o": 41.0, "h": 41.55, "l": 40.25, "c": 40.3, "v": 6979029}]}