{"9908": [{"date": "2025/04/30", "o": 31.0, "h": 31.0, "l": 30.7, "c": 30.75, "v": 184149}, {"date": "2025/05/02", "o": 30.75, "h": 30.9, "l": 30.75, "c": 30.8, "v": 82003}, {"date": "2025/05/05", "o": 30.8, "h": 31.25, "l": 30.8, "c": 31.2, "v": 172120}, {"date": "2025/05/06", "o": 31.45, "h": 31.45, "l": 30.9, "c": 31.2, "v": 130020}, {"date": "2025/05/07", "o": 31.4, "h": 31.6, "l": 31.25, "c": 31.35, "v": 127500}, {"date": "2025/05/08", "o": 31.35, "h": 31.45, "l": 31.0, "c": 31.25, "v": 124309}, {"date": "2025/05/09", "o": 31.2, "h": 31.4, "l": 31.1, "c": 31.25, "v": 64031}, {"date": "2025/05/12", "o": 31.7, "h": 31.7, "l": 31.15, "c": 31.15, "v": 44075}, {"date": "2025/05/13", "o": 31.0, "h": 31.1, "l": 30.9, "c": 31.05, "v": 93000}, {"date": "2025/05/14", "o": 31.05, "h": 31.4, "l": 30.9, "c": 31.1, "v": 119185}, {"date": "2025/05/15", "o": 31.0, "h": 31.1, "l": 30.95, "c": 31.0, "v": 53003}, {"date": "2025/05/16", "o": 30.95, "h": 31.1, "l": 30.95, "c": 31.05, "v": 57000}, {"date": "2025/05/19", "o": 31.0, "h": 31.15, "l": 30.9, "c": 31.0, "v": 88048}, {"date": "2025/05/20", "o": 31.1, "h": 31.1, "l": 30.95, "c": 31.1, "v": 55004}, {"date": "2025/05/21", "o": 31.1, "h": 31.3, "l": 31.05, "c": 31.25, "v": 63000}, {"date": "2025/05/22", "o": 30.9, "h": 31.2, "l": 30.9, "c": 30.9, "v": 174004}, {"date": "2025/05/23", "o": 30.85, "h": 31.25, "l": 30.85, "c": 30.85, "v": 87000}, {"date": "2025/05/26", "o": 30.85, "h": 31.4, "l": 30.85, "c": 31.25, "v": 196043}, {"date": "2025/05/27", "o": 31.2, "h": 31.2, "l": 30.85, "c": 30.9, "v": 111011}, {"date": "2025/05/28", "o": 30.95, "h": 31.0, "l": 30.85, "c": 30.95, "v": 58006}, {"date": "2025/05/29", "o": 30.95, "h": 31.05, "l": 30.8, "c": 31.05, "v": 62004}, {"date": "2025/06/02", "o": 30.9, "h": 30.9, "l": 30.75, "c": 30.8, "v": 164063}, {"date": "2025/06/03", "o": 30.8, "h": 30.9, "l": 30.7, "c": 30.7, "v": 58004}, {"date": "2025/06/04", "o": 30.7, "h": 30.95, "l": 30.7, "c": 30.8, "v": 34003}, {"date": "2025/06/05", "o": 30.75, "h": 30.9, "l": 30.75, "c": 30.9, "v": 14756}, {"date": "2025/06/06", "o": 30.95, "h": 31.0, "l": 30.9, "c": 31.0, "v": 39752}, {"date": "2025/06/09", "o": 31.0, "h": 31.1, "l": 30.85, "c": 30.85, "v": 61160}, {"date": "2025/06/10", "o": 30.9, "h": 31.3, "l": 30.9, "c": 30.95, "v": 119404}, {"date": "2025/06/11", "o": 30.85, "h": 31.2, "l": 30.85, "c": 31.2, "v": 86160}, {"date": "2025/06/12", "o": 31.0, "h": 31.2, "l": 31.0, "c": 31.15, "v": 28374}, {"date": "2025/06/13", "o": 30.8, "h": 31.3, "l": 30.8, "c": 31.15, "v": 132260}, {"date": "2025/06/16", "o": 31.15, "h": 31.3, "l": 31.0, "c": 31.25, "v": 101340}, {"date": "2025/06/17", "o": 31.1, "h": 31.3, "l": 31.1, "c": 31.25, "v": 109000}, {"date": "2025/06/18", "o": 31.0, "h": 31.15, "l": 30.9, "c": 31.15, "v": 81113}, {"date": "2025/06/19", "o": 31.0, "h": 31.0, "l": 30.8, "c": 30.85, "v": 142000}, {"date": "2025/06/20", "o": 30.85, "h": 30.9, "l": 30.65, "c": 30.8, "v": 173605}, {"date": "2025/06/23", "o": 30.7, "h": 31.05, "l": 30.7, "c": 31.0, "v": 62000}, {"date": "2025/06/24", "o": 30.85, "h": 31.2, "l": 30.85, "c": 31.15, "v": 123715}, {"date": "2025/06/25", "o": 31.05, "h": 31.2, "l": 31.05, "c": 31.2, "v": 53000}, {"date": "2025/06/26", "o": 31.2, "h": 31.3, "l": 31.05, "c": 31.3, "v": 87134}, {"date": "2025/06/27", "o": 31.2, "h": 31.35, "l": 31.1, "c": 31.25, "v": 111962}, {"date": "2025/06/30", "o": 31.1, "h": 31.4, "l": 31.05, "c": 31.35, "v": 103027}, {"date": "2025/07/01", "o": 31.3, "h": 31.5, "l": 31.3, "c": 31.45, "v": 90110}, {"date": "2025/07/02", "o": 31.15, "h": 31.3, "l": 31.1, "c": 31.1, "v": 45100}, {"date": "2025/07/03", "o": 31.15, "h": 31.3, "l": 31.15, "c": 31.3, "v": 39062}, {"date": "2025/07/04", "o": 31.3, "h": 31.35, "l": 31.1, "c": 31.35, "v": 52033}, {"date": "2025/07/07", "o": 31.2, "h": 31.3, "l": 31.1, "c": 31.25, "v": 34130}, {"date": "2025/07/08", "o": 31.15, "h": 31.3, "l": 31.15, "c": 31.3, "v": 66000}, {"date": "2025/07/09", "o": 31.2, "h": 31.2, "l": 31.1, "c": 31.1, "v": 11165}, {"date": "2025/07/10", "o": 30.9, "h": 31.1, "l": 30.9, "c": 31.0, "v": 68100}, {"date": "2025/07/11", "o": 31.2, "h": 31.2, "l": 31.0, "c": 31.1, "v": 7025}, {"date": "2025/07/14", "o": 31.25, "h": 31.25, "l": 30.95, "c": 30.95, "v": 42346}, {"date": "2025/07/15", "o": 30.9, "h": 31.25, "l": 30.9, "c": 30.95, "v": 108000}, {"date": "2025/07/16", "o": 30.95, "h": 31.15, "l": 30.95, "c": 30.95, "v": 97781}, {"date": "2025/07/17", "o": 30.95, "h": 31.2, "l": 30.95, "c": 31.15, "v": 35000}, {"date": "2025/07/18", "o": 31.25, "h": 31.25, "l": 31.0, "c": 31.2, "v": 108455}, {"date": "2025/07/21", "o": 31.1, "h": 31.2, "l": 31.05, "c": 31.05, "v": 51158}, {"date": "2025/07/22", "o": 31.0, "h": 31.15, "l": 30.9, "c": 30.9, "v": 157765}, {"date": "2025/07/23", "o": 31.05, "h": 31.15, "l": 31.0, "c": 31.1, "v": 82001}, {"date": "2025/07/24", "o": 31.15, "h": 31.2, "l": 31.05, "c": 31.1, "v": 57000}, {"date": "2025/07/25", "o": 31.0, "h": 31.2, "l": 31.0, "c": 31.05, "v": 69175}, {"date": "2025/07/28", "o": 31.1, "h": 31.25, "l": 31.05, "c": 31.2, "v": 91263}, {"date": "2025/07/29", "o": 31.2, "h": 31.25, "l": 31.15, "c": 31.25, "v": 166560}, {"date": "2025/07/30", "o": 30.05, "h": 30.25, "l": 30.05, "c": 30.1, "v": 205407}, {"date": "2025/07/31", "o": 30.1, "h": 30.2, "l": 30.05, "c": 30.1, "v": 95107}, {"date": "2025/08/04", "o": 30.0, "h": 30.1, "l": 29.95, "c": 29.95, "v": 240753}, {"date": "2025/08/05", "o": 29.95, "h": 30.0, "l": 29.95, "c": 29.95, "v": 239000}, {"date": "2025/08/06", "o": 29.95, "h": 30.0, "l": 29.9, "c": 30.0, "v": 323001}, {"date": "2025/08/07", "o": 30.0, "h": 30.1, "l": 29.95, "c": 30.1, "v": 148000}, {"date": "2025/08/08", "o": 29.9, "h": 30.15, "l": 29.9, "c": 30.05, "v": 85360}, {"date": "2025/08/11", "o": 29.9, "h": 30.05, "l": 29.9, "c": 30.05, "v": 120248}, {"date": "2025/08/12", "o": 30.05, "h": 30.1, "l": 30.0, "c": 30.1, "v": 40023}, {"date": "2025/08/13", "o": 30.1, "h": 30.15, "l": 30.0, "c": 30.1, "v": 64000}, {"date": "2025/08/14", "o": 30.1, "h": 30.1, "l": 30.05, "c": 30.1, "v": 110365}, {"date": "2025/08/15", "o": 30.1, "h": 30.1, "l": 30.0, "c": 30.1, "v": 68000}, {"date": "2025/08/18", "o": 30.1, "h": 30.1, "l": 29.95, "c": 30.1, "v": 79102}, {"date": "2025/08/19", "o": 30.0, "h": 30.1, "l": 29.95, "c": 30.05, "v": 66003}, {"date": "2025/08/20", "o": 30.1, "h": 30.1, "l": 30.05, "c": 30.1, "v": 69189}, {"date": "2025/08/21", "o": 30.1, "h": 30.1, "l": 30.0, "c": 30.05, "v": 64001}, {"date": "2025/08/22", "o": 30.0, "h": 30.1, "l": 29.95, "c": 30.0, "v": 55200}, {"date": "2025/08/25", "o": 30.1, "h": 30.1, "l": 30.0, "c": 30.05, "v": 36397}, {"date": "2025/08/26", "o": 30.0, "h": 30.1, "l": 30.0, "c": 30.0, "v": 76001}, {"date": "2025/08/27", "o": 29.95, "h": 30.0, "l": 29.95, "c": 29.95, "v": 81098}, {"date": "2025/08/28", "o": 29.95, "h": 30.05, "l": 29.95, "c": 29.95, "v": 45073}, {"date": "2025/08/29", "o": 30.0, "h": 30.05, "l": 30.0, "c": 30.05, "v": 42085}, {"date": "2025/09/01", "o": 30.05, "h": 30.1, "l": 30.0, "c": 30.0, "v": 39000}, {"date": "2025/09/02", "o": 29.95, "h": 30.05, "l": 29.95, "c": 30.0, "v": 28237}, {"date": "2025/09/03", "o": 29.95, "h": 30.05, "l": 29.95, "c": 30.0, "v": 25237}, {"date": "2025/09/04", "o": 29.95, "h": 30.05, "l": 29.95, "c": 30.0, "v": 41500}, {"date": "2025/09/05", "o": 30.0, "h": 30.1, "l": 30.0, "c": 30.1, "v": 70419}, {"date": "2025/09/08", "o": 30.0, "h": 30.1, "l": 30.0, "c": 30.1, "v": 19000}, {"date": "2025/09/09", "o": 30.05, "h": 30.1, "l": 30.0, "c": 30.1, "v": 75046}, {"date": "2025/09/10", "o": 30.0, "h": 30.15, "l": 30.0, "c": 30.1, "v": 85979}, {"date": "2025/09/11", "o": 30.0, "h": 30.1, "l": 29.95, "c": 30.1, "v": 200794}, {"date": "2025/09/12", "o": 30.0, "h": 30.1, "l": 30.0, "c": 30.1, "v": 37033}, {"date": "2025/09/15", "o": 30.1, "h": 30.1, "l": 30.0, "c": 30.0, "v": 74075}, {"date": "2025/09/16", "o": 30.0, "h": 30.05, "l": 29.95, "c": 29.95, "v": 70731}, {"date": "2025/09/17", "o": 30.0, "h": 30.05, "l": 29.95, "c": 29.95, "v": 125009}, {"date": "2025/09/18", "o": 30.0, "h": 30.05, "l": 29.95, "c": 30.0, "v": 81250}, {"date": "2025/09/19", "o": 30.0, "h": 30.05, "l": 29.95, "c": 30.05, "v": 118010}, {"date": "2025/09/22", "o": 30.1, "h": 30.15, "l": 30.0, "c": 30.05, "v": 97000}, {"date": "2025/09/23", "o": 30.0, "h": 30.0, "l": 29.95, "c": 30.0, "v": 141252}, {"date": "2025/09/24", "o": 30.0, "h": 30.1, "l": 29.95, "c": 30.0, "v": 49000}, {"date": "2025/09/25", "o": 30.1, "h": 30.1, "l": 29.95, "c": 30.05, "v": 67079}, {"date": "2025/09/26", "o": 30.0, "h": 30.05, "l": 29.95, "c": 30.05, "v": 51612}, {"date": "2025/09/30", "o": 30.1, "h": 30.1, "l": 30.0, "c": 30.1, "v": 59100}, {"date": "2025/10/01", "o": 30.1, "h": 30.1, "l": 29.95, "c": 30.1, "v": 53000}, {"date": "2025/10/02", "o": 30.1, "h": 30.1, "l": 30.0, "c": 30.1, "v": 36000}, {"date": "2025/10/03", "o": 30.0, "h": 30.05, "l": 29.95, "c": 30.0, "v": 49143}, {"date": "2025/10/07", "o": 30.05, "h": 30.05, "l": 29.9, "c": 30.05, "v": 104000}, {"date": "2025/10/08", "o": 30.05, "h": 30.05, "l": 29.95, "c": 29.95, "v": 101798}, {"date": "2025/10/09", "o": 30.0, "h": 30.0, "l": 29.9, "c": 29.95, "v": 209038}, {"date": "2025/10/13", "o": 30.05, "h": 30.05, "l": 29.9, "c": 29.9, "v": 190000}, {"date": "2025/10/14", "o": 29.9, "h": 30.0, "l": 29.9, "c": 30.0, "v": 78031}, {"date": "2025/10/15", "o": 29.9, "h": 30.0, "l": 29.9, "c": 29.9, "v": 57902}, {"date": "2025/10/16", "o": 29.95, "h": 30.0, "l": 29.85, "c": 30.0, "v": 153630}, {"date": "2025/10/17", "o": 30.0, "h": 30.05, "l": 29.9, "c": 29.9, "v": 85055}, {"date": "2025/10/20", "o": 29.95, "h": 29.95, "l": 29.9, "c": 29.95, "v": 39166}, {"date": "2025/10/21", "o": 30.0, "h": 30.0, "l": 29.9, "c": 29.9, "v": 164983}, {"date": "2025/10/22", "o": 29.9, "h": 30.0, "l": 29.9, "c": 30.0, "v": 105069}, {"date": "2025/10/23", "o": 30.0, "h": 30.0, "l": 29.9, "c": 29.95, "v": 22000}, {"date": "2025/10/27", "o": 29.95, "h": 30.0, "l": 29.9, "c": 30.0, "v": 142033}, {"date": "2025/10/28", "o": 30.05, "h": 30.05, "l": 29.9, "c": 29.95, "v": 39000}, {"date": "2025/10/29", "o": 30.0, "h": 30.0, "l": 29.95, "c": 29.95, "v": 50600}, {"date": "2025/10/30", "o": 29.95, "h": 30.0, "l": 29.9, "c": 29.95, "v": 101000}, {"date": "2025/10/31", "o": 30.0, "h": 30.0, "l": 29.95, "c": 30.0, "v": 33237}, {"date": "2025/11/03", "o": 29.9, "h": 29.95, "l": 29.85, "c": 29.9, "v": 117400}, {"date": "2025/11/04", "o": 29.85, "h": 29.95, "l": 29.85, "c": 29.95, "v": 77000}, {"date": "2025/11/05", "o": 29.95, "h": 29.95, "l": 29.85, "c": 29.9, "v": 95262}, {"date": "2025/11/06", "o": 30.0, "h": 30.0, "l": 29.9, "c": 29.9, "v": 60160}, {"date": "2025/11/07", "o": 29.95, "h": 30.0, "l": 29.95, "c": 30.0, "v": 103804}, {"date": "2025/11/10", "o": 30.0, "h": 30.0, "l": 29.95, "c": 30.0, "v": 33176}, {"date": "2025/11/11", "o": 29.95, "h": 30.05, "l": 29.95, "c": 30.0, "v": 51458}, {"date": "2025/11/12", "o": 30.0, "h": 30.05, "l": 29.9, "c": 30.0, "v": 95226}, {"date": "2025/11/13", "o": 30.0, "h": 30.05, "l": 29.9, "c": 30.05, "v": 100000}, {"date": "2025/11/14", "o": 30.05, "h": 30.05, "l": 29.9, "c": 30.0, "v": 84037}, {"date": "2025/11/17", "o": 29.95, "h": 30.1, "l": 29.95, "c": 30.1, "v": 89398}, {"date": "2025/11/18", "o": 30.0, "h": 30.1, "l": 30.0, "c": 30.1, "v": 116000}, {"date": "2025/11/19", "o": 30.5, "h": 30.5, "l": 29.95, "c": 30.1, "v": 171165}, {"date": "2025/11/20", "o": 30.0, "h": 30.1, "l": 29.9, "c": 30.05, "v": 154000}, {"date": "2025/11/21", "o": 30.1, "h": 30.1, "l": 29.95, "c": 30.1, "v": 82061}, {"date": "2025/11/24", "o": 30.1, "h": 30.1, "l": 29.95, "c": 30.1, "v": 75100}, {"date": "2025/11/25", "o": 29.95, "h": 30.1, "l": 29.95, "c": 30.1, "v": 139144}, {"date": "2025/11/26", "o": 30.1, "h": 30.1, "l": 30.0, "c": 30.1, "v": 56935}, {"date": "2025/11/27", "o": 29.95, "h": 30.15, "l": 29.95, "c": 30.1, "v": 43133}, {"date": "2025/11/28", "o": 29.95, "h": 30.15, "l": 29.95, "c": 30.15, "v": 85176}, {"date": "2025/12/01", "o": 29.95, "h": 30.15, "l": 29.95, "c": 30.05, "v": 78034}, {"date": "2025/12/02", "o": 30.1, "h": 30.15, "l": 29.95, "c": 30.0, "v": 141105}, {"date": "2025/12/03", "o": 30.05, "h": 30.05, "l": 30.0, "c": 30.05, "v": 114160}, {"date": "2025/12/04", "o": 29.95, "h": 30.1, "l": 29.95, "c": 30.1, "v": 73395}, {"date": "2025/12/05", "o": 30.0, "h": 30.15, "l": 30.0, "c": 30.15, "v": 40263}, {"date": "2025/12/08", "o": 30.0, "h": 30.1, "l": 30.0, "c": 30.1, "v": 93370}, {"date": "2025/12/09", "o": 29.95, "h": 30.1, "l": 29.95, "c": 30.0, "v": 36000}, {"date": "2025/12/10", "o": 30.0, "h": 30.1, "l": 30.0, "c": 30.0, "v": 63000}, {"date": "2025/12/11", "o": 30.0, "h": 30.05, "l": 29.95, "c": 30.05, "v": 36294}, {"date": "2025/12/12", "o": 30.2, "h": 30.25, "l": 29.95, "c": 30.0, "v": 155000}, {"date": "2025/12/15", "o": 30.1, "h": 30.1, "l": 29.95, "c": 30.0, "v": 164200}, {"date": "2025/12/16", "o": 29.9, "h": 30.05, "l": 29.75, "c": 30.05, "v": 549085}, {"date": "2025/12/17", "o": 30.05, "h": 30.05, "l": 29.95, "c": 29.95, "v": 86055}, {"date": "2025/12/18", "o": 30.0, "h": 30.05, "l": 29.9, "c": 30.0, "v": 116183}, {"date": "2025/12/19", "o": 29.85, "h": 30.0, "l": 29.85, "c": 30.0, "v": 43066}, {"date": "2025/12/22", "o": 30.0, "h": 30.0, "l": 29.95, "c": 29.95, "v": 39303}, {"date": "2025/12/23", "o": 29.95, "h": 30.0, "l": 29.9, "c": 29.9, "v": 80001}, {"date": "2025/12/24", "o": 30.0, "h": 30.0, "l": 29.9, "c": 29.95, "v": 90344}, {"date": "2025/12/26", "o": 29.95, "h": 30.0, "l": 29.9, "c": 29.9, "v": 96237}, {"date": "2025/12/29", "o": 29.95, "h": 30.0, "l": 29.9, "c": 29.95, "v": 115020}, {"date": "2025/12/30", "o": 29.95, "h": 29.95, "l": 29.85, "c": 29.9, "v": 137000}, {"date": "2025/12/31", "o": 29.95, "h": 30.0, "l": 29.85, "c": 30.0, "v": 148061}, {"date": "2026/01/02", "o": 30.0, "h": 30.0, "l": 29.85, "c": 29.85, "v": 160000}, {"date": "2026/01/05", "o": 29.85, "h": 29.9, "l": 29.8, "c": 29.85, "v": 96000}, {"date": "2026/01/06", "o": 29.85, "h": 29.95, "l": 29.85, "c": 29.85, "v": 82004}, {"date": "2026/01/07", "o": 29.85, "h": 29.9, "l": 29.85, "c": 29.85, "v": 95000}, {"date": "2026/01/08", "o": 29.85, "h": 29.9, "l": 29.85, "c": 29.85, "v": 85794}, {"date": "2026/01/09", "o": 29.85, "h": 29.9, "l": 29.85, "c": 29.85, "v": 223033}, {"date": "2026/01/12", "o": 29.85, "h": 29.9, "l": 29.8, "c": 29.8, "v": 230477}, {"date": "2026/01/13", "o": 29.9, "h": 29.9, "l": 29.8, "c": 29.85, "v": 113210}, {"date": "2026/01/14", "o": 29.9, "h": 29.9, "l": 29.85, "c": 29.9, "v": 158200}, {"date": "2026/01/15", "o": 29.85, "h": 29.95, "l": 29.85, "c": 29.9, "v": 188970}, {"date": "2026/01/16", "o": 29.9, "h": 30.05, "l": 29.9, "c": 29.95, "v": 89050}, {"date": "2026/01/19", "o": 29.85, "h": 29.95, "l": 29.85, "c": 29.85, "v": 162116}, {"date": "2026/01/20", "o": 29.8, "h": 30.0, "l": 29.8, "c": 29.85, "v": 114150}, {"date": "2026/01/21", "o": 29.85, "h": 29.9, "l": 29.8, "c": 29.9, "v": 92159}, {"date": "2026/01/22", "o": 29.9, "h": 29.9, "l": 29.75, "c": 29.8, "v": 232181}, {"date": "2026/01/23", "o": 29.8, "h": 29.8, "l": 29.75, "c": 29.8, "v": 180611}, {"date": "2026/01/26", "o": 29.8, "h": 29.8, "l": 29.7, "c": 29.7, "v": 351296}, {"date": "2026/01/27", "o": 29.75, "h": 29.85, "l": 29.7, "c": 29.75, "v": 74163}, {"date": "2026/01/28", "o": 29.8, "h": 29.85, "l": 29.7, "c": 29.8, "v": 383001}, {"date": "2026/01/29", "o": 29.75, "h": 29.95, "l": 29.75, "c": 29.95, "v": 122001}, {"date": "2026/01/30", "o": 29.8, "h": 29.9, "l": 29.75, "c": 29.9, "v": 85319}, {"date": "2026/02/02", "o": 29.95, "h": 29.95, "l": 29.75, "c": 29.75, "v": 120000}, {"date": "2026/02/03", "o": 29.75, "h": 29.75, "l": 29.7, "c": 29.7, "v": 166000}, {"date": "2026/02/04", "o": 29.7, "h": 29.8, "l": 29.7, "c": 29.8, "v": 121000}, {"date": "2026/02/05", "o": 29.8, "h": 29.9, "l": 29.75, "c": 29.8, "v": 123100}, {"date": "2026/02/06", "o": 29.8, "h": 29.85, "l": 29.75, "c": 29.75, "v": 124175}, {"date": "2026/02/09", "o": 29.9, "h": 29.9, "l": 29.75, "c": 29.85, "v": 100376}, {"date": "2026/02/10", "o": 29.8, "h": 29.95, "l": 29.8, "c": 29.95, "v": 59100}, {"date": "2026/02/11", "o": 30.0, "h": 30.1, "l": 29.85, "c": 29.9, "v": 303469}, {"date": "2026/02/23", "o": 30.3, "h": 30.3, "l": 29.9, "c": 30.0, "v": 269220}, {"date": "2026/02/24", "o": 30.05, "h": 30.1, "l": 29.9, "c": 30.0, "v": 118041}, {"date": "2026/02/25", "o": 29.95, "h": 30.1, "l": 29.9, "c": 30.0, "v": 133237}, {"date": "2026/02/26", "o": 30.1, "h": 30.1, "l": 29.9, "c": 30.05, "v": 163059}, {"date": "2026/03/02", "o": 30.25, "h": 30.25, "l": 30.05, "c": 30.15, "v": 241285}, {"date": "2026/03/03", "o": 30.4, "h": 30.95, "l": 30.0, "c": 30.15, "v": 627444}, {"date": "2026/03/04", "o": 30.85, "h": 33.15, "l": 30.7, "c": 31.3, "v": 7381700}, {"date": "2026/03/05", "o": 31.75, "h": 31.75, "l": 30.2, "c": 30.75, "v": 2352796}, {"date": "2026/03/06", "o": 31.5, "h": 33.0, "l": 31.45, "c": 31.95, "v": 5143568}, {"date": "2026/03/09", "o": 33.3, "h": 35.1, "l": 33.3, "c": 34.5, "v": 19187465}, {"date": "2026/03/10", "o": 31.05, "h": 31.05, "l": 31.05, "c": 31.05, "v": 2140975}, {"date": "2026/03/11", "o": 30.05, "h": 30.65, "l": 29.2, "c": 30.45, "v": 5959943}, {"date": "2026/03/12", "o": 31.55, "h": 31.9, "l": 30.5, "c": 30.85, "v": 3345134}, {"date": "2026/03/13", "o": 31.75, "h": 32.8, "l": 30.4, "c": 30.4, "v": 2916286}, {"date": "2026/03/16", "o": 30.3, "h": 30.65, "l": 30.2, "c": 30.45, "v": 1991173}, {"date": "2026/03/17", "o": 30.4, "h": 30.4, "l": 30.05, "c": 30.15, "v": 1282214}, {"date": "2026/03/18", "o": 30.3, "h": 30.3, "l": 30.0, "c": 30.0, "v": 967500}, {"date": "2026/03/19", "o": 31.4, "h": 31.8, "l": 30.35, "c": 30.4, "v": 2947039}, {"date": "2026/03/20", "o": 30.15, "h": 30.45, "l": 30.05, "c": 30.1, "v": 1065509}, {"date": "2026/03/23", "o": 30.7, "h": 31.1, "l": 29.95, "c": 29.95, "v": 2120000}, {"date": "2026/03/24", "o": 29.95, "h": 30.0, "l": 29.75, "c": 29.9, "v": 940077}, {"date": "2026/03/25", "o": 30.0, "h": 30.0, "l": 29.8, "c": 29.9, "v": 910000}, {"date": "2026/03/26", "o": 29.8, "h": 30.2, "l": 29.8, "c": 30.1, "v": 541000}, {"date": "2026/03/27", "o": 30.25, "h": 30.45, "l": 30.0, "c": 30.0, "v": 413083}, {"date": "2026/03/30", "o": 30.0, "h": 30.2, "l": 29.95, "c": 29.95, "v": 543165}, {"date": "2026/03/31", "o": 30.0, "h": 30.0, "l": 29.75, "c": 29.75, "v": 699678}, {"date": "2026/04/01", "o": 29.9, "h": 29.95, "l": 29.8, "c": 29.85, "v": 290000}, {"date": "2026/04/02", "o": 29.95, "h": 30.0, "l": 29.85, "c": 29.9, "v": 290100}, {"date": "2026/04/07", "o": 29.95, "h": 29.95, "l": 29.8, "c": 29.9, "v": 276143}, {"date": "2026/04/08", "o": 29.85, "h": 29.85, "l": 29.7, "c": 29.75, "v": 928340}, {"date": "2026/04/09", "o": 29.8, "h": 29.9, "l": 29.7, "c": 29.75, "v": 445000}, {"date": "2026/04/10", "o": 29.75, "h": 29.9, "l": 29.75, "c": 29.75, "v": 294000}, {"date": "2026/04/13", "o": 29.75, "h": 29.85, "l": 29.75, "c": 29.8, "v": 219000}, {"date": "2026/04/14", "o": 29.75, "h": 29.9, "l": 29.7, "c": 29.8, "v": 731961}, {"date": "2026/04/15", "o": 29.8, "h": 29.95, "l": 29.65, "c": 29.95, "v": 912300}, {"date": "2026/04/16", "o": 29.9, "h": 29.95, "l": 29.75, "c": 29.8, "v": 352062}, {"date": "2026/04/17", "o": 29.95, "h": 29.95, "l": 29.75, "c": 29.85, "v": 298120}, {"date": "2026/04/20", "o": 29.85, "h": 29.9, "l": 29.7, "c": 29.9, "v": 693303}, {"date": "2026/04/21", "o": 29.95, "h": 29.95, "l": 29.7, "c": 29.7, "v": 388000}, {"date": "2026/04/22", "o": 29.7, "h": 29.9, "l": 29.7, "c": 29.7, "v": 246520}, {"date": "2026/04/23", "o": 29.7, "h": 29.75, "l": 29.35, "c": 29.55, "v": 1188501}, {"date": "2026/04/24", "o": 29.6, "h": 29.7, "l": 29.5, "c": 29.5, "v": 372014}, {"date": "2026/04/27", "o": 29.55, "h": 29.55, "l": 29.4, "c": 29.45, "v": 467368}, {"date": "2026/04/28", "o": 29.85, "h": 29.85, "l": 29.5, "c": 29.6, "v": 197007}, {"date": "2026/04/29", "o": 29.85, "h": 29.85, "l": 29.6, "c": 29.8, "v": 294001}, {"date": "2026/04/30", "o": 29.65, "h": 29.7, "l": 29.55, "c": 29.6, "v": 223220}]}